DEFINITIVOS/BCD A BIN/Comp.v
module Comp (
    input  wire [4:0] c_in,
    output wire       zero
);

    assign zero = (c_in == 5'd0);

endmodule

DEFINITIVOS/BCD A BIN/Comp_TB.v
module Comp_TB;

    reg  [4:0] c_in;
    wire       zero;
    integer    i;

    Comp dut (
        .c_in (c_in),
        .zero (zero)
    );

    initial begin
        `ifdef BENCH
            $dumpfile("Comp_TB.vcd");
            $dumpvars(0, Comp_TB);
        `endif

        for (i = 0; i < 32; i = i + 1) begin
            c_in = i[4:0];
            #10;
        end

        $finish;
    end

endmodule

DEFINITIVOS/BCD A BIN/Comp_TB.vcd
$date
	Mon Jul 13 18:51:50 2026
$end
$version
	Icarus Verilog
$end
$timescale
	1s
$end
$scope module Comp_TB $end
$var wire 1 ! zero $end
$var reg 5 " c_in [4:0] $end
$var integer 32 # i [31:0] $end
$scope module dut $end
$var wire 5 $ c_in [4:0] $end
$var wire 1 ! zero $end
$upscope $end
$upscope $end
$enddefinitions $end
$comment Show the parameter values. $end
$dumpall
$end
#0
$dumpvars
b0 $
b0 #
b0 "
1!
$end
#10
0!
b1 "
b1 $
b1 #
#20
b10 "
b10 $
b10 #
#30
b11 "
b11 $
b11 #
#40
b100 "
b100 $
b100 #
#50
b101 "
b101 $
b101 #
#60
b110 "
b110 $
b110 #
#70
b111 "
b111 $
b111 #
#80
b1000 "
b1000 $
b1000 #
#90
b1001 "
b1001 $
b1001 #
#100
b1010 "
b1010 $
b1010 #
#110
b1011 "
b1011 $
b1011 #
#120
b1100 "
b1100 $
b1100 #
#130
b1101 "
b1101 $
b1101 #
#140
b1110 "
b1110 $
b1110 #
#150
b1111 "
b1111 $
b1111 #
#160
b10000 "
b10000 $
b10000 #
#170
b10001 "
b10001 $
b10001 #
#180
b10010 "
b10010 $
b10010 #
#190
b10011 "
b10011 $
b10011 #
#200
b10100 "
b10100 $
b10100 #
#210
b10101 "
b10101 $
b10101 #
#220
b10110 "
b10110 $
b10110 #
#230
b10111 "
b10111 $
b10111 #
#240
b11000 "
b11000 $
b11000 #
#250
b11001 "
b11001 $
b11001 #
#260
b11010 "
b11010 $
b11010 #
#270
b11011 "
b11011 $
b11011 #
#280
b11100 "
b11100 $
b11100 #
#290
b11101 "
b11101 $
b11101 #
#300
b11110 "
b11110 $
b11110 #
#310
b11111 "
b11111 $
b11111 #
#320
b100000 #
