DEFINITIVOS/BCD A BIN/Control.v
module Control (
    input  wire clk,
    input  wire rst_n,
    input  wire init,
    input  wire zero,
    output reg  ld,
    output reg  shift,
    output reg  dec,
    output reg  subtract,
    output reg  done
);

    localparam S_START    = 3'd0;
    localparam S_CHECK1   = 3'd1;
    localparam S_FINAL    = 3'd2;
    localparam S_CHECK2   = 3'd3;
    localparam S_SUBTRACT = 3'd4;
    localparam S_SHIFTDEC = 3'd5;

    reg [2:0] state, next_state;

    always @(posedge clk or negedge rst_n) begin
        if (!rst_n) state <= S_START;
        else        state <= next_state;
    end

    always @(*) begin
        case (state)
            S_START:    next_state = init ? S_CHECK1 : S_START;
            S_CHECK1:   next_state = zero ? S_FINAL   : S_CHECK2;
            S_FINAL:    next_state = S_START;
            S_CHECK2:   next_state = S_SUBTRACT;
            S_SUBTRACT: next_state = S_SHIFTDEC;
            S_SHIFTDEC: next_state = S_CHECK1;
            default:    next_state = S_START;
        endcase
    end

    always @(*) begin
        ld = 1'b0; shift = 1'b0; dec = 1'b0; subtract = 1'b0; done = 1'b0;
        case (state)
            S_START:    ld       = 1'b1;
            S_SUBTRACT: subtract = 1'b1;
            S_SHIFTDEC: begin shift = 1'b1; dec = 1'b1; end
            S_FINAL:    done     = 1'b1;
            default:    ;
        endcase
    end

endmodule

DEFINITIVOS/BCD A BIN/Control_TB.v
module Control_TB;

    reg  clk, rst_n, init, zero;
    wire ld, shift, dec, subtract, done;

    Control dut (
        .clk      (clk),
        .rst_n    (rst_n),
        .init     (init),
        .zero     (zero),
        .ld       (ld),
        .shift    (shift),
        .dec      (dec),
        .subtract (subtract),
        .done     (done)
    );

    always #5 clk = ~clk;

    task step;
        begin
            @(posedge clk);
            #1;
        end
    endtask

    initial begin
        clk = 0; rst_n = 0; init = 0; zero = 0;

        `ifdef BENCH
            $dumpfile("Control_TB.vcd");
            $dumpvars(0, Control_TB);
        `endif

        step; rst_n = 1;

        init = 1; step;   // START -> CHECK1
        init = 0;

        zero = 0; step;   // CHECK1 -> CHECK2
        step;              // CHECK2 -> SUBTRACT
        step;              // SUBTRACT -> SHIFTDEC
        step;              // SHIFTDEC -> CHECK1

        zero = 1; step;   // CHECK1 -> FINAL
        step;              // FINAL -> START

        $finish;
    end

endmodule

DEFINITIVOS/BCD A BIN/Control_TB.vcd
$date
	Mon Jul 13 18:53:28 2026
$end
$version
	Icarus Verilog
$end
$timescale
	1s
$end
$scope module Control_TB $end
$var wire 1 ! subtract $end
$var wire 1 " shift $end
$var wire 1 # ld $end
$var wire 1 $ done $end
$var wire 1 % dec $end
$var reg 1 & clk $end
$var reg 1 ' init $end
$var reg 1 ( rst_n $end
$var reg 1 ) zero $end
$scope module dut $end
$var wire 1 & clk $end
$var wire 1 ' init $end
$var wire 1 ( rst_n $end
$var wire 1 ) zero $end
$var parameter 3 * S_CHECK1 $end
$var parameter 3 + S_CHECK2 $end
$var parameter 3 , S_FINAL $end
$var parameter 3 - S_SHIFTDEC $end
$var parameter 3 . S_START $end
$var parameter 3 / S_SUBTRACT $end
$var reg 1 % dec $end
$var reg 1 $ done $end
$var reg 1 # ld $end
$var reg 3 0 next_state [2:0] $end
$var reg 1 " shift $end
$var reg 3 1 state [2:0] $end
$var reg 1 ! subtract $end
$upscope $end
$scope task step $end
$upscope $end
$upscope $end
$enddefinitions $end
$comment Show the parameter values. $end
$dumpall
b100 /
b0 .
b101 -
b10 ,
b11 +
b1 *
$end
#0
$dumpvars
b0 1
b0 0
0)
0(
0'
0&
0%
0$
1#
0"
0!
$end
#5
1&
#6
b1 0
1'
1(
#10
0&
#15
0#
b11 0
b1 1
1&
#16
0'
#20
0&
#25
b100 0
b11 1
1&
#30
0&
#35
1!
b101 0
b100 1
1&
#40
0&
#45
1%
1"
0!
b1 0
b101 1
1&
#50
0&
#55
0%
0"
b11 0
b1 1
1&
#56
b10 0
1)
#60
0&
#65
1$
b0 0
b10 1
1&
#70
0&
#75
1#
0$
b0 1
1&
