DEFINITIVOS/BCD A BIN/RegBCD.v
module RegBCD (
    input  wire        clk,
    input  wire        rst_n,
    input  wire        ld,
    input  wire        shift,
    input  wire        subtract,
    input  wire [19:0] bcd_in,
    input  wire [35:0] corrected_in,
    output reg  [35:0] reg_out
);

    always @(posedge clk or negedge rst_n) begin
        if (!rst_n)
            reg_out <= 36'b0;
        else if (ld)
            reg_out <= {bcd_in, 16'b0};
        else if (subtract)
            reg_out <= corrected_in;
        else if (shift)
            reg_out <= reg_out >> 1;
    end

endmodule

DEFINITIVOS/BCD A BIN/RegBCD_TB.v
module RegBCD_TB;

    reg         clk, rst_n, ld, shift, subtract;
    reg  [19:0] bcd_in;
    reg  [35:0] corrected_in;
    wire [35:0] reg_out;

    RegBCD dut (
        .clk          (clk),
        .rst_n        (rst_n),
        .ld           (ld),
        .shift        (shift),
        .subtract     (subtract),
        .bcd_in       (bcd_in),
        .corrected_in (corrected_in),
        .reg_out      (reg_out)
    );

    always #5 clk = ~clk;

    initial begin
        clk = 0; rst_n = 0; ld = 0; shift = 0; subtract = 0;
        bcd_in = 20'h0; corrected_in = 36'h0;

        `ifdef BENCH
            $dumpfile("RegBCD_TB.vcd");
            $dumpvars(0, RegBCD_TB);
        `endif

        @(negedge clk); rst_n = 1;

        bcd_in = 20'h12345;
        @(negedge clk); ld = 1;
        @(negedge clk); ld = 0;

        corrected_in = 36'hABCDE1234;
        @(negedge clk); subtract = 1;
        @(negedge clk); subtract = 0;

        @(negedge clk); shift = 1;
        @(negedge clk);
        @(negedge clk); shift = 0;

        @(negedge clk);
        $finish;
    end

endmodule

DEFINITIVOS/BCD A BIN/RegBCD_TB.vcd
$date
	Mon Jul 13 18:57:31 2026
$end
$version
	Icarus Verilog
$end
$timescale
	1s
$end
$scope module RegBCD_TB $end
$var wire 36 ! reg_out [35:0] $end
$var reg 20 " bcd_in [19:0] $end
$var reg 1 # clk $end
$var reg 36 $ corrected_in [35:0] $end
$var reg 1 % ld $end
$var reg 1 & rst_n $end
$var reg 1 ' shift $end
$var reg 1 ( subtract $end
$scope module dut $end
$var wire 20 ) bcd_in [19:0] $end
$var wire 1 # clk $end
$var wire 36 * corrected_in [35:0] $end
$var wire 1 % ld $end
$var wire 1 & rst_n $end
$var wire 1 ' shift $end
$var wire 1 ( subtract $end
$var reg 36 + reg_out [35:0] $end
$upscope $end
$upscope $end
$enddefinitions $end
$comment Show the parameter values. $end
$dumpall
$end
#0
$dumpvars
b0 +
b0 *
b0 )
0(
0'
0&
0%
b0 $
0#
b0 "
b0 !
$end
#5
1#
#10
b10010001101000101 "
b10010001101000101 )
1&
0#
#15
1#
#20
1%
0#
#25
b100100011010001010000000000000000 !
b100100011010001010000000000000000 +
1#
#30
b101010111100110111100001001000110100 $
b101010111100110111100001001000110100 *
0%
0#
#35
1#
#40
1(
0#
#45
b101010111100110111100001001000110100 !
b101010111100110111100001001000110100 +
1#
#50
0(
0#
#55
1#
#60
1'
0#
#65
b10101011110011011110000100100011010 !
b10101011110011011110000100100011010 +
1#
#70
0#
#75
b1010101111001101111000010010001101 !
b1010101111001101111000010010001101 +
1#
#80
0'
0#
