DEFINITIVOS/BCD A BIN/RegC.v
module RegC (
    input  wire       clk,
    input  wire       rst_n,
    input  wire       ld,
    input  wire       dec,
    output reg  [4:0] c_out
);

    always @(posedge clk or negedge rst_n) begin
        if (!rst_n)
            c_out <= 5'd0;
        else if (ld)
            c_out <= 5'd16;
        else if (dec)
            c_out <= c_out - 5'd1;
    end

endmodule

DEFINITIVOS/BCD A BIN/RegC_TB.v
module RegC_TB;

    reg        clk, rst_n, ld, dec;
    wire [4:0] c_out;
    integer    i;

    RegC dut (
        .clk   (clk),
        .rst_n (rst_n),
        .ld    (ld),
        .dec   (dec),
        .c_out (c_out)
    );

    always #5 clk = ~clk;

    initial begin
        clk = 0; rst_n = 0; ld = 0; dec = 0;

        `ifdef BENCH
            $dumpfile("RegC_TB.vcd");
            $dumpvars(0, RegC_TB);
        `endif

        @(negedge clk); rst_n = 1;

        @(negedge clk); ld = 1;
        @(negedge clk); ld = 0;

        for (i = 0; i < 16; i = i + 1) begin
            @(negedge clk); dec = 1;
            @(negedge clk); dec = 0;
        end

        @(negedge clk);
        $finish;
    end

endmodule

DEFINITIVOS/BCD A BIN/RegC_TB.vcd
$date
	Mon Jul 13 18:59:18 2026
$end
$version
	Icarus Verilog
$end
$timescale
	1s
$end
$scope module RegC_TB $end
$var wire 5 ! c_out [4:0] $end
$var reg 1 " clk $end
$var reg 1 # dec $end
$var reg 1 $ ld $end
$var reg 1 % rst_n $end
$var integer 32 & i [31:0] $end
$scope module dut $end
$var wire 1 " clk $end
$var wire 1 # dec $end
$var wire 1 $ ld $end
$var wire 1 % rst_n $end
$var reg 5 ' c_out [4:0] $end
$upscope $end
$upscope $end
$enddefinitions $end
$comment Show the parameter values. $end
$dumpall
$end
#0
$dumpvars
b0 '
bx &
0%
0$
0#
0"
b0 !
$end
#5
1"
#10
1%
0"
#15
1"
#20
1$
0"
#25
b10000 !
b10000 '
1"
#30
b0 &
0$
0"
#35
1"
#40
1#
0"
#45
b1111 !
b1111 '
1"
#50
b1 &
0#
0"
#55
1"
#60
1#
0"
#65
b1110 !
b1110 '
1"
#70
b10 &
0#
0"
#75
1"
#80
1#
0"
#85
b1101 !
b1101 '
1"
#90
b11 &
0#
0"
#95
1"
#100
1#
0"
#105
b1100 !
b1100 '
1"
#110
b100 &
0#
0"
#115
1"
#120
1#
0"
#125
b1011 !
b1011 '
1"
#130
b101 &
0#
0"
#135
1"
#140
1#
0"
#145
b1010 !
b1010 '
1"
#150
b110 &
0#
0"
#155
1"
#160
1#
0"
#165
b1001 !
b1001 '
1"
#170
b111 &
0#
0"
#175
1"
#180
1#
0"
#185
b1000 !
b1000 '
1"
#190
b1000 &
0#
0"
#195
1"
#200
1#
0"
#205
b111 !
b111 '
1"
#210
b1001 &
0#
0"
#215
1"
#220
1#
0"
#225
b110 !
b110 '
1"
#230
b1010 &
0#
0"
#235
1"
#240
1#
0"
#245
b101 !
b101 '
1"
#250
b1011 &
0#
0"
#255
1"
#260
1#
0"
#265
b100 !
b100 '
1"
#270
b1100 &
0#
0"
#275
1"
#280
1#
0"
#285
b11 !
b11 '
1"
#290
b1101 &
0#
0"
#295
1"
#300
1#
0"
#305
b10 !
b10 '
1"
#310
b1110 &
0#
0"
#315
1"
#320
1#
0"
#325
b1 !
b1 '
1"
#330
b1111 &
0#
0"
#335
1"
#340
1#
0"
#345
b0 !
b0 '
1"
#350
b10000 &
0#
0"
