DEFINITIVOS/RAIZ/Control.v
module Control (
    clk,
    rst,
    INIT,
    ZERO,
    MAYORIGUAL,
    LD,
    SHIFT,
    SUBTRACT,
    SETRAIZ,
    DEC,
    DONE
);

input clk;
input rst;
input INIT;
input ZERO;
input MAYORIGUAL;
output reg LD;
output reg SHIFT;
output reg SUBTRACT;
output reg SETRAIZ;
output reg DEC;
output reg DONE;

parameter Start  = 3'b000;
parameter Check1 = 3'b001;
parameter Shift1 = 3'b010;
parameter Check2 = 3'b011;
parameter Update = 3'b100; // MAYORIGUAL=1: resta y fija el bit de raiz en 1
parameter Shift2 = 3'b101; // MAYORIGUAL=0: solo corre el bit de raiz (bit 0)
parameter Dec    = 3'b110;
parameter Final  = 3'b111;

reg [2:0] STATE;

always @(posedge clk or posedge rst) begin
    if (rst)
        STATE <= Start;
    else begin
        case (STATE)
            Start:  STATE <= INIT ? Check1 : Start;
            Check1: STATE <= ZERO ? Final  : Shift1;
            Shift1: STATE <= Check2;
            Check2: STATE <= MAYORIGUAL ? Update : Shift2;
            Update: STATE <= Dec;
            Shift2: STATE <= Dec;
            Dec:    STATE <= Check1;
            Final:  STATE <= Start;
            default: STATE <= Start;
        endcase
    end
end

always @(*) begin
    LD = 0; SHIFT = 0; SUBTRACT = 0; SETRAIZ = 0; DEC = 0; DONE = 0;
    case (STATE)
        Start:  begin LD = 1; end         
        Shift1: begin SHIFT = 1; end
        Check2: begin end
        Update: begin SUBTRACT = 1; SETRAIZ = 1; end
        Shift2: begin SETRAIZ = 1; end
        Dec:    begin DEC = 1; end
        Final:  begin DONE = 1; end
        default: begin end
    endcase
end

`ifdef BENCH
reg [8*20:1] estado_nombre;
always @(*) begin
    case (STATE)
        Start:  estado_nombre = "START";
        Check1: estado_nombre = "CHECK1";
        Shift1: estado_nombre = "SHIFT1";
        Check2: estado_nombre = "CHECK2";
        Update: estado_nombre = "UPDATE";
        Shift2: estado_nombre = "SHIFT2";
        Dec:    estado_nombre = "DEC";
        Final:  estado_nombre = "FINAL";
        default: estado_nombre = "unknown";
    endcase
end
`endif

endmodule

DEFINITIVOS/RAIZ/Control_TB.v
module Control_TB;
reg clk;
reg rst;
reg INIT;
reg ZERO;
reg MAYORIGUAL;
wire LD, SHIFT, SUBTRACT, SETRAIZ, DEC, DONE;

Control uut (
    .clk(clk), .rst(rst), .INIT(INIT), .ZERO(ZERO), .MAYORIGUAL(MAYORIGUAL),
    .LD(LD), .SHIFT(SHIFT), .SUBTRACT(SUBTRACT), .SETRAIZ(SETRAIZ), .DEC(DEC), .DONE(DONE)
);

initial begin
    clk = 0;
    forever #20 clk = ~clk;
end

initial begin
    $dumpfile("Control_TB.vcd");
    $dumpvars(0, Control_TB);

    rst = 1; INIT = 0; ZERO = 0; MAYORIGUAL = 0;
    @(posedge clk);
    rst = 0;

    @(posedge clk);
    INIT = 1;
    @(posedge clk);
    INIT = 0;
    repeat(2) begin
        @(posedge clk); // Check1 -> Shift1
        MAYORIGUAL = 1;
        @(posedge clk); // Shift1 -> Check2
        @(posedge clk); // Check2 -> Update
        @(posedge clk); // Update -> Dec
        @(posedge clk); // Dec -> Check1
    end
    MAYORIGUAL = 0;
    @(posedge clk); // Check1 -> Shift1
    @(posedge clk); // Shift1 -> Check2
    @(posedge clk); // Check2 -> Shift2
    @(posedge clk); // Shift2 -> Dec
    @(posedge clk); // Dec -> Check1
    ZERO = 1;
    @(posedge clk); // Check1 -> Final
    @(posedge clk); // Final -> Start
    ZERO = 0;
    #40;

    $finish;
end

endmodule

DEFINITIVOS/RAIZ/Control_TB.vcd
$date
	Mon Jul 13 22:45:03 2026
$end
$version
	Icarus Verilog
$end
$timescale
	1s
$end
$scope module Control_TB $end
$var wire 1 ! SUBTRACT $end
$var wire 1 " SHIFT $end
$var wire 1 # SETRAIZ $end
$var wire 1 $ LD $end
$var wire 1 % DONE $end
$var wire 1 & DEC $end
$var reg 1 ' INIT $end
$var reg 1 ( MAYORIGUAL $end
$var reg 1 ) ZERO $end
$var reg 1 * clk $end
$var reg 1 + rst $end
$scope module uut $end
$var wire 1 ' INIT $end
$var wire 1 ( MAYORIGUAL $end
$var wire 1 ) ZERO $end
$var wire 1 * clk $end
$var wire 1 + rst $end
$var parameter 3 , Check1 $end
$var parameter 3 - Check2 $end
$var parameter 3 . Dec $end
$var parameter 3 / Final $end
$var parameter 3 0 Shift1 $end
$var parameter 3 1 Shift2 $end
$var parameter 3 2 Start $end
$var parameter 3 3 Update $end
$var reg 1 & DEC $end
$var reg 1 % DONE $end
$var reg 1 $ LD $end
$var reg 1 # SETRAIZ $end
$var reg 1 " SHIFT $end
$var reg 3 4 STATE [2:0] $end
$var reg 1 ! SUBTRACT $end
$var reg 160 5 estado_nombre [160:1] $end
$upscope $end
$upscope $end
$enddefinitions $end
$comment Show the parameter values. $end
$dumpall
b100 3
b0 2
b101 1
b10 0
b111 /
b110 .
b11 -
b1 ,
$end
#0
$dumpvars
b101001101010100010000010101001001010100 5
b0 4
1+
0*
0)
0(
0'
0&
0%
1$
0#
0"
0!
$end
#20
0+
1*
#40
0*
#60
0$
b10000110100100001000101010000110100101100110001 5
b1 4
1'
1*
#80
0*
#100
b10100110100100001001001010001100101010000110001 5
1"
b10 4
0'
1*
#120
0*
#140
0"
b10000110100100001000101010000110100101100110010 5
b11 4
1(
1*
#160
0*
#180
b10101010101000001000100010000010101010001000101 5
1#
1!
b100 4
1*
#200
0*
#220
1&
0#
0!
b10001000100010101000011 5
b110 4
1*
#240
0*
#260
b10000110100100001000101010000110100101100110001 5
0&
b1 4
1*
#280
0*
#300
1"
b10100110100100001001001010001100101010000110001 5
b10 4
1*
#320
0*
#340
b10000110100100001000101010000110100101100110010 5
0"
b11 4
1*
#360
0*
#380
1#
1!
b10101010101000001000100010000010101010001000101 5
b100 4
1*
#400
0*
#420
b10001000100010101000011 5
1&
0#
0!
b110 4
1*
#440
0*
#460
0&
b10000110100100001000101010000110100101100110001 5
b1 4
1*
#480
0*
#500
b10100110100100001001001010001100101010000110001 5
1"
b10 4
0(
1*
#520
0*
#540
0"
b10000110100100001000101010000110100101100110010 5
b11 4
1*
#560
0*
#580
b10100110100100001001001010001100101010000110010 5
1#
b101 4
1*
#600
0*
#620
1&
0#
b10001000100010101000011 5
b110 4
1*
#640
0*
#660
b10000110100100001000101010000110100101100110001 5
0&
b1 4
1*
#680
0*
#700
1%
b100011001001001010011100100000101001100 5
b111 4
1)
1*
#720
0*
#740
b101001101010100010000010101001001010100 5
1$
0%
b0 4
1*
#760
0*
#780
0)
1*
