DEFINITIVOS/RAIZ/RegC.v
module RegC (
    clk,
    ld,
    dec,
    count
);
input clk;
input ld;
input dec;
output [3:0] count;

reg [3:0] cnt;
assign count = cnt;

always @(posedge clk) begin
    if (ld)
        cnt <= 4'd8;
    else if (dec)
        cnt <= cnt - 1'b1;
end

endmodule

DEFINITIVOS/RAIZ/RegC_TB.v
module RegC_TB;
reg clk;
reg ld;
reg dec;
wire [3:0] count;

RegC uut (.clk(clk), .ld(ld), .dec(dec), .count(count));

initial begin
    clk = 0;
    forever #20 clk = ~clk;
end

initial begin
    $dumpfile("RegC_TB.vcd");
    $dumpvars(0, RegC_TB);

    ld = 0; dec = 0;
    @(posedge clk);
    ld = 1;
    @(posedge clk);
    ld = 0;
    dec = 1;
    repeat(8) @(posedge clk);
    dec = 0;
    #40;

    $finish;
end

endmodule

DEFINITIVOS/RAIZ/RegC_TB.vcd
$date
	Mon Jul 13 22:48:28 2026
$end
$version
	Icarus Verilog
$end
$timescale
	1s
$end
$scope module RegC_TB $end
$var wire 4 ! count [3:0] $end
$var reg 1 " clk $end
$var reg 1 # dec $end
$var reg 1 $ ld $end
$scope module uut $end
$var wire 1 " clk $end
$var wire 4 % count [3:0] $end
$var wire 1 # dec $end
$var wire 1 $ ld $end
$var reg 4 & cnt [3:0] $end
$upscope $end
$upscope $end
$enddefinitions $end
$comment Show the parameter values. $end
$dumpall
$end
#0
$dumpvars
bx &
bx %
0$
0#
0"
bx !
$end
#20
b1000 !
b1000 %
b1000 &
1$
1"
#40
0"
#60
1#
0$
1"
#80
0"
#100
b111 !
b111 %
b111 &
1"
#120
0"
#140
b110 !
b110 %
b110 &
1"
#160
0"
#180
b101 !
b101 %
b101 &
1"
#200
0"
#220
b100 !
b100 %
b100 &
1"
#240
0"
#260
b11 !
b11 %
b11 &
1"
#280
0"
#300
b10 !
b10 %
b10 &
1"
#320
0"
#340
b1 !
b1 %
b1 &
1"
#360
0"
#380
b0 !
b0 %
b0 &
0#
1"
