DEFINITIVOS/RAIZ/RegResiduo.v
module RegResiduo (
    clk,
    ld,
    subtract,
    shift,
    ShiftIn,
    T,
    Residuo
);
input clk;
input ld;
input subtract;
input shift;
input  [1:0]  ShiftIn; // 2 bits mas significativos de RegRad, antes de su corrimiento
input  [15:0] T;
output [15:0] Residuo;

reg [15:0] reg_residuo;
assign Residuo = reg_residuo;

always @(posedge clk) begin
    if (ld)
        reg_residuo <= 16'b0;
    else if (subtract)
        reg_residuo <= reg_residuo - T;
    else if (shift)
        reg_residuo <= {reg_residuo[13:0], ShiftIn};
end

endmodule

DEFINITIVOS/RAIZ/RegResiduo_TB.v
module RegResiduo_TB;
reg clk;
reg ld;
reg subtract;
reg shift;
reg [1:0] ShiftIn;
reg [15:0] T;
wire [15:0] Residuo;

RegResiduo uut (.clk(clk), .ld(ld), .subtract(subtract), .shift(shift), .ShiftIn(ShiftIn), .T(T), .Residuo(Residuo));

initial begin
    clk = 0;
    forever #20 clk = ~clk;
end

initial begin
    $dumpfile("RegResiduo_TB.vcd");
    $dumpvars(0, RegResiduo_TB);

    ld = 0; subtract = 0; shift = 0; ShiftIn = 2'b00; T = 16'd0;
    @(posedge clk);
    ld = 1;
    @(posedge clk);
    ld = 0;
    ShiftIn = 2'b11;
    shift = 1;
    @(posedge clk);
    shift = 0;
    T = 16'd5;
    subtract = 1;
    @(posedge clk);
    subtract = 0;
    ShiftIn = 2'b01;
    shift = 1;
    repeat(3) @(posedge clk);
    shift = 0;
    #40;

    $finish;
end

endmodule

DEFINITIVOS/RAIZ/RegResiduo_TB.vcd
$date
	Mon Jul 13 22:52:45 2026
$end
$version
	Icarus Verilog
$end
$timescale
	1s
$end
$scope module RegResiduo_TB $end
$var wire 16 ! Residuo [15:0] $end
$var reg 2 " ShiftIn [1:0] $end
$var reg 16 # T [15:0] $end
$var reg 1 $ clk $end
$var reg 1 % ld $end
$var reg 1 & shift $end
$var reg 1 ' subtract $end
$scope module uut $end
$var wire 16 ( Residuo [15:0] $end
$var wire 2 ) ShiftIn [1:0] $end
$var wire 16 * T [15:0] $end
$var wire 1 $ clk $end
$var wire 1 % ld $end
$var wire 1 & shift $end
$var wire 1 ' subtract $end
$var reg 16 + reg_residuo [15:0] $end
$upscope $end
$upscope $end
$enddefinitions $end
$comment Show the parameter values. $end
$dumpall
$end
#0
$dumpvars
bx +
b0 *
b0 )
bx (
0'
0&
0%
0$
b0 #
b0 "
bx !
$end
#20
b0 !
b0 (
b0 +
1%
1$
#40
0$
#60
1&
b11 "
b11 )
0%
1$
#80
0$
#100
b1111111111111011 !
b1111111111111011 (
b1111111111111011 +
1'
b101 #
b101 *
0&
1$
#120
0$
#140
b1111111111110110 !
b1111111111110110 (
b1111111111110110 +
1&
b1 "
b1 )
0'
1$
#160
0$
#180
b1111111111011001 !
b1111111111011001 (
b1111111111011001 +
1$
#200
0$
#220
b1111111101100101 !
b1111111101100101 (
b1111111101100101 +
1$
#240
0$
#260
0&
1$
