DEFINITIVOS/MULTIPLICACION/Control.v
module Control (
    clk,
    rst,
    INIT,
    ZERO,
    LSB,
    LD,
    ADD,
    SHIFT,
    DONE
);
input clk;
input rst;
input INIT;
input ZERO;
input LSB;
output reg LD;
output reg ADD;
output reg SHIFT;
output reg DONE;

parameter Start  = 3'b000; // LD=1
parameter Check1 = 3'b001; // pregunta ZERO (C==0)
parameter Check2 = 3'b010; // pregunta LSB(B)
parameter AddSt  = 3'b011; // LBS(B)=1 -> ADD=1, luego pasa por Shift
parameter ShiftSt= 3'b100; // A<<1, B>>1, C=C-1
parameter Final  = 3'b101; // ZERO=1 -> DONE=1

reg [2:0] STATE;

always @(posedge clk or posedge rst) begin
    if (rst)
        STATE <= Start;
    else begin
        case (STATE)
            Start: begin
                if (INIT)
                    STATE <= Check1;
                else
                    STATE <= Start;
            end
            Check1: begin
                if (ZERO)
                    STATE <= Final;
                else
                    STATE <= Check2;
            end
            Check2: begin
                if (LSB)
                    STATE <= AddSt;
                else
                    STATE <= ShiftSt;
            end
            AddSt: begin
                STATE <= ShiftSt; 
            end
            ShiftSt: begin
                STATE <= Check1;
            end
            Final: begin
                STATE <= Start;
            end
            default: STATE <= Start;
        endcase
    end
end

always @(*) begin
    case (STATE)
        Start: begin
            LD    = 1;
            ADD   = 0;
            SHIFT = 0;
            DONE  = 0;
        end
        Check1: begin
            LD    = 0;
            ADD   = 0;
            SHIFT = 0;
            DONE  = 0;
        end
        Check2: begin
            LD    = 0;
            ADD   = 0;
            SHIFT = 0;
            DONE  = 0;
        end
        AddSt: begin
            LD    = 0;
            ADD   = 1;
            SHIFT = 0;
            DONE  = 0;
        end
        ShiftSt: begin
            LD    = 0;
            ADD   = 0;
            SHIFT = 1;
            DONE  = 0;
        end
        Final: begin
            LD    = 0;
            ADD   = 0;
            SHIFT = 0;
            DONE  = 1;
        end
        default: begin
            LD    = 0;
            ADD   = 0;
            SHIFT = 0;
            DONE  = 0;
        end
    endcase
end

`ifdef BENCH
reg [8*20:1] estado_nombre;
always @(*) begin
    case (STATE)
        Start:   estado_nombre = "START";
        Check1:  estado_nombre = "CHECK1";
        Check2:  estado_nombre = "CHECK2";
        AddSt:   estado_nombre = "ADD";
        ShiftSt: estado_nombre = "SHIFT";
        Final:   estado_nombre = "FINAL";
        default: estado_nombre = "unknown";
    endcase
end
`endif

endmodule

DEFINITIVOS/MULTIPLICACION/Control_TB.v
module Control_TB;
reg clk;
reg rst;
reg INIT;
reg ZERO;
reg LSB;
wire LD;
wire ADD;
wire SHIFT;
wire DONE;

Control uut (
    .clk(clk), .rst(rst), .INIT(INIT), .ZERO(ZERO), .LSB(LSB),
    .LD(LD), .ADD(ADD), .SHIFT(SHIFT), .DONE(DONE)
);

initial begin
    clk = 0;
    forever #20 clk = ~clk;
end

initial begin
    $dumpfile("Control_TB.vcd");
    $dumpvars(0, Control_TB);

    rst = 1;
    INIT = 0;
    ZERO = 0;
    LSB = 0;
    @(posedge clk);
    rst = 0;

    // Caso: LSB=1 (pasa por ADD y SHIFT), luego LSB=0 (solo SHIFT), luego ZERO=1 (Final)
    @(posedge clk);
    INIT = 1;
    @(posedge clk);
    INIT = 0;
    @(posedge clk); // Check1 -> Check2 (ZERO=0)
    LSB = 1;
    @(posedge clk); // Check2 -> AddSt
    @(posedge clk); // AddSt -> ShiftSt
    @(posedge clk); // ShiftSt -> Check1
    LSB = 0;
    @(posedge clk); // Check1 -> Check2 (ZERO=0)
    @(posedge clk); // Check2 -> ShiftSt
    @(posedge clk); // ShiftSt -> Check1
    ZERO = 1;
    @(posedge clk); // Check1 -> Final
    @(posedge clk);
    ZERO = 0;
    #40;

    $finish;
end

endmodule

DEFINITIVOS/MULTIPLICACION/Control_TB.vcd
$date
	Mon Jul 13 12:55:42 2026
$end
$version
	Icarus Verilog
$end
$timescale
	1s
$end
$scope module Control_TB $end
$var wire 1 ! SHIFT $end
$var wire 1 " LD $end
$var wire 1 # DONE $end
$var wire 1 $ ADD $end
$var reg 1 % INIT $end
$var reg 1 & LSB $end
$var reg 1 ' ZERO $end
$var reg 1 ( clk $end
$var reg 1 ) rst $end
$scope module uut $end
$var wire 1 % INIT $end
$var wire 1 & LSB $end
$var wire 1 ' ZERO $end
$var wire 1 ( clk $end
$var wire 1 ) rst $end
$var parameter 3 * AddSt $end
$var parameter 3 + Check1 $end
$var parameter 3 , Check2 $end
$var parameter 3 - Final $end
$var parameter 3 . ShiftSt $end
$var parameter 3 / Start $end
$var reg 1 $ ADD $end
$var reg 1 # DONE $end
$var reg 1 " LD $end
$var reg 1 ! SHIFT $end
$var reg 3 0 STATE [2:0] $end
$var reg 160 1 estado_nombre [160:1] $end
$upscope $end
$upscope $end
$enddefinitions $end
$comment Show the parameter values. $end
$dumpall
b0 /
b100 .
b101 -
b10 ,
b1 +
b11 *
$end
#0
$dumpvars
b101001101010100010000010101001001010100 1
b0 0
1)
0(
0'
0&
0%
0$
0#
1"
0!
$end
#20
0)
1(
#40
0(
#60
0"
b10000110100100001000101010000110100101100110001 1
b1 0
1%
1(
#80
0(
#100
b10000110100100001000101010000110100101100110010 1
b10 0
0%
1(
#120
0(
#140
1$
b10000010100010001000100 1
b11 0
1&
1(
#160
0(
#180
b101001101001000010010010100011001010100 1
1!
0$
b100 0
1(
#200
0(
#220
0!
b10000110100100001000101010000110100101100110001 1
b1 0
1(
#240
0(
#260
b10000110100100001000101010000110100101100110010 1
b10 0
0&
1(
#280
0(
#300
1!
b101001101001000010010010100011001010100 1
b100 0
1(
#320
0(
#340
b10000110100100001000101010000110100101100110001 1
0!
b1 0
1(
#360
0(
#380
1#
b100011001001001010011100100000101001100 1
b101 0
1'
1(
#400
0(
#420
b101001101010100010000010101001001010100 1
0#
1"
b0 0
1(
#440
0(
#460
0'
1(
