DEFINITIVOS/MULTIPLICACION/Counter.v
module Counter #(parameter N = 8, parameter CW = 4) (
    clk,
    Id,
    Dec,
    count
);

input clk;
input Id;
input Dec;
output [CW-1:0] count;

reg [CW-1:0] cnt;
assign count = cnt;

always @(posedge clk) begin
    if (Id)
        cnt <= N[CW-1:0];
    else if (Dec)
        cnt <= cnt - 1'b1;
end

endmodule

DEFINITIVOS/MULTIPLICACION/Counter_TB.v
module Counter_TB;
reg clk;
reg Id;
reg Dec;
wire [3:0] count;

Counter #(.N(8), .CW(4)) uut (.clk(clk), .Id(Id), .Dec(Dec), .count(count));

initial begin
    clk = 0;
    forever #20 clk = ~clk;
end

initial begin
    $dumpfile("Counter_TB.vcd");
    $dumpvars(0, Counter_TB);

    Id = 0;
    Dec = 0;
    @(posedge clk);
    Id = 1;
    @(posedge clk);
    Id = 0;
    @(posedge clk);
    Dec = 1;
    repeat(8) @(posedge clk); // de 8 a 0
    Dec = 0;
    #40;

    $finish;
end

endmodule

DEFINITIVOS/MULTIPLICACION/Counter_TB.vcd
$date
	Mon Jul 13 12:57:56 2026
$end
$version
	Icarus Verilog
$end
$timescale
	1s
$end
$scope module Counter_TB $end
$var wire 4 ! count [3:0] $end
$var reg 1 " Dec $end
$var reg 1 # Id $end
$var reg 1 $ clk $end
$scope module uut $end
$var wire 1 " Dec $end
$var wire 1 # Id $end
$var wire 1 $ clk $end
$var wire 4 % count [3:0] $end
$var parameter 32 & CW $end
$var parameter 32 ' N $end
$var reg 4 ( cnt [3:0] $end
$upscope $end
$upscope $end
$enddefinitions $end
$comment Show the parameter values. $end
$dumpall
b1000 '
b100 &
$end
#0
$dumpvars
bx (
bx %
0$
0#
0"
bx !
$end
#20
b1000 !
b1000 %
b1000 (
1#
1$
#40
0$
#60
0#
1$
#80
0$
#100
b111 !
b111 %
b111 (
1"
1$
#120
0$
#140
b110 !
b110 %
b110 (
1$
#160
0$
#180
b101 !
b101 %
b101 (
1$
#200
0$
#220
b100 !
b100 %
b100 (
1$
#240
0$
#260
b11 !
b11 %
b11 (
1$
#280
0$
#300
b10 !
b10 %
b10 (
1$
#320
0$
#340
b1 !
b1 %
b1 (
1$
#360
0$
#380
b0 !
b0 %
b0 (
1$
#400
0$
#420
0"
1$
