DEFINITIVOS/MULTIPLICACION/RegA.v
module RegA #(parameter N = 8) (
    clk,
    init_a,
    shift_l,
    A,
    RegA_out
);
input clk;
input init_a;
input shift_l;
input  [N-1:0]   A;
output [2*N-1:0] RegA_out;

reg [2*N-1:0] regA;
assign RegA_out = regA;

always @(posedge clk) begin
    if (init_a)
        regA <= {{N{1'b0}}, A};
    else if (shift_l)
        regA <= regA << 1;
end

endmodule

DEFINITIVOS/MULTIPLICACION/RegA_TB.v
module RegA_TB;
reg clk;
reg init_a;
reg shift_l;
reg [7:0] A;
wire [15:0] RegA_out;

RegA #(.N(8)) uut (.clk(clk), .init_a(init_a), .shift_l(shift_l), .A(A), .RegA_out(RegA_out));

initial begin
    clk = 0;
    forever #20 clk = ~clk;
end

initial begin
    $dumpfile("RegA_TB.vcd");
    $dumpvars(0, RegA_TB);

    init_a = 0;
    shift_l = 0;
    A = 8'd5;
    @(posedge clk);
    init_a = 1;
    @(posedge clk);
    init_a = 0;
    shift_l = 1;
    repeat(3) @(posedge clk);
    shift_l = 0;
    #40;

    A = 8'd200;
    @(posedge clk);
    init_a = 1;
    @(posedge clk);
    init_a = 0;
    shift_l = 1;
    repeat(4) @(posedge clk);
    shift_l = 0;
    #40;

    $finish;
end

endmodule

DEFINITIVOS/MULTIPLICACION/RegA_TB.vcd
$date
	Mon Jul 13 13:06:31 2026
$end
$version
	Icarus Verilog
$end
$timescale
	1s
$end
$scope module RegA_TB $end
$var wire 16 ! RegA_out [15:0] $end
$var reg 8 " A [7:0] $end
$var reg 1 # clk $end
$var reg 1 $ init_a $end
$var reg 1 % shift_l $end
$scope module uut $end
$var wire 8 & A [7:0] $end
$var wire 16 ' RegA_out [15:0] $end
$var wire 1 # clk $end
$var wire 1 $ init_a $end
$var wire 1 % shift_l $end
$var parameter 32 ( N $end
$var reg 16 ) regA [15:0] $end
$upscope $end
$upscope $end
$enddefinitions $end
$comment Show the parameter values. $end
$dumpall
b1000 (
$end
#0
$dumpvars
bx )
bx '
b101 &
0%
0$
0#
b101 "
bx !
$end
#20
b101 !
b101 '
b101 )
1$
1#
#40
0#
#60
1%
0$
1#
#80
0#
#100
b1010 !
b1010 '
b1010 )
1#
#120
0#
#140
b10100 !
b10100 '
b10100 )
1#
#160
0#
#180
0%
1#
#200
0#
#220
b11001000 !
b11001000 '
b11001000 )
1$
1#
b11001000 "
b11001000 &
#240
0#
#260
1%
0$
1#
#280
0#
#300
b110010000 !
b110010000 '
b110010000 )
1#
#320
0#
#340
b1100100000 !
b1100100000 '
b1100100000 )
1#
#360
0#
#380
b11001000000 !
b11001000000 '
b11001000000 )
1#
#400
0#
#420
b110010000000 !
b110010000000 '
b110010000000 )
0%
1#
