DEFINITIVOS/MULTIPLICACION/RegB.v
module RegB #(parameter N = 8) (
    clk,
    init_b,
    shift_r,
    B,
    LSB
);
input clk;
input init_b;
input shift_r;
input [N-1:0] B;
output LSB;

reg [N-1:0] regB;
assign LSB = regB[0];

always @(posedge clk) begin
    if (init_b)
        regB <= B;
    else if (shift_r)
        regB <= regB >> 1;
end

endmodule

DEFINITIVOS/MULTIPLICACION/RegB_TB.v
module RegB_TB;
reg clk;
reg init_b;
reg shift_r;
reg [7:0] B;
wire LSB;

RegB #(.N(8)) uut (.clk(clk), .init_b(init_b), .shift_r(shift_r), .B(B), .LSB(LSB));

initial begin
    clk = 0;
    forever #20 clk = ~clk;
end

initial begin
    $dumpfile("RegB_TB.vcd");
    $dumpvars(0, RegB_TB);

    init_b = 0;
    shift_r = 0;
    B = 8'b00010110; // 22, para ver LSB alternando: 0,1,1,0,1...
    @(posedge clk);
    init_b = 1;
    @(posedge clk);
    init_b = 0;
    shift_r = 1;
    repeat(8) @(posedge clk);
    shift_r = 0;
    #40;

    $finish;
end

endmodule

DEFINITIVOS/MULTIPLICACION/RegB_TB.vcd
$date
	Mon Jul 13 13:08:57 2026
$end
$version
	Icarus Verilog
$end
$timescale
	1s
$end
$scope module RegB_TB $end
$var wire 1 ! LSB $end
$var reg 8 " B [7:0] $end
$var reg 1 # clk $end
$var reg 1 $ init_b $end
$var reg 1 % shift_r $end
$scope module uut $end
$var wire 8 & B [7:0] $end
$var wire 1 # clk $end
$var wire 1 $ init_b $end
$var wire 1 % shift_r $end
$var wire 1 ! LSB $end
$var parameter 32 ' N $end
$var reg 8 ( regB [7:0] $end
$upscope $end
$upscope $end
$enddefinitions $end
$comment Show the parameter values. $end
$dumpall
b1000 '
$end
#0
$dumpvars
bx (
b10110 &
0%
0$
0#
b10110 "
x!
$end
#20
0!
b10110 (
1$
1#
#40
0#
#60
1%
0$
1#
#80
0#
#100
1!
b1011 (
1#
#120
0#
#140
b101 (
1#
#160
0#
#180
0!
b10 (
1#
#200
0#
#220
1!
b1 (
1#
#240
0#
#260
0!
b0 (
1#
#280
0#
#300
1#
#320
0#
#340
1#
#360
0#
#380
0%
1#
