DEFINITIVOS/DIVISION/Control.v
module Control (
    clk,
    rst,
    INIT,
    ZERO,
    RESIDUOCOMP,
    SETCOCIENTE,
    SETRESIDUO,
    LD,
    SHIFT,
    DEC,
    DONE
);
input clk;
input rst;
input INIT;
input ZERO;
input RESIDUOCOMP;
output reg SETCOCIENTE;
output reg SETRESIDUO;
output reg LD;
output reg SHIFT;
output reg DEC;
output reg DONE;

parameter Start      = 3'b000; // LD=1
parameter Check1     = 3'b001; // pregunta ZERO (C==0)
parameter Shift      = 3'b010; // (Residuo,Dividendo)<<1
parameter Check2     = 3'b011; // pregunta RESIDUOCOMP
parameter Setco      = 3'b100; // RESIDUOCOMP=0
parameter Setcodi    = 3'b101; // RESIDUOCOMP=1 -> SETCOCIENTE=1, SETRESIDUO=1
parameter Counterdec = 3'b110; // DEC=1
parameter End        = 3'b111; // DONE=1

reg [2:0] STATE;

always @(posedge clk or posedge rst) begin
    if (rst)
        STATE <= Start;
    else begin
        case (STATE)
            Start: begin
                if (INIT)
                    STATE <= Check1;
                else
                    STATE <= Start;
            end
            Check1: begin
                if (ZERO)
                    STATE <= End;
                else
                    STATE <= Shift;
            end
            Shift: begin
                STATE <= Check2;
            end
            Check2: begin
                if (RESIDUOCOMP)
                    STATE <= Setcodi;
                else
                    STATE <= Setco;
            end
            Setco: begin
                STATE <= Counterdec;
            end
            Setcodi: begin
                STATE <= Counterdec;
            end
            Counterdec: begin
                STATE <= Check1;
            end
            End: begin
                STATE <= Start;
            end
            default: STATE <= Start;
        endcase
    end
end

always @(*) begin
    case (STATE)
        Start: begin
            SETCOCIENTE = 0; SETRESIDUO = 0; LD = 1; SHIFT = 0; DEC = 0; DONE = 0;
        end
        Check1: begin
            SETCOCIENTE = 0; SETRESIDUO = 0; LD = 0; SHIFT = 0; DEC = 0; DONE = 0;
        end
        Shift: begin
            SETCOCIENTE = 0; SETRESIDUO = 0; LD = 0; SHIFT = 1; DEC = 0; DONE = 0;
        end
        Check2: begin
            SETCOCIENTE = 0; SETRESIDUO = 0; LD = 0; SHIFT = 0; DEC = 0; DONE = 0;
        end
        Setco: begin
            SETCOCIENTE = 0; SETRESIDUO = 0; LD = 0; SHIFT = 0; DEC = 0; DONE = 0;
        end
        Setcodi: begin
            SETCOCIENTE = 1; SETRESIDUO = 1; LD = 0; SHIFT = 0; DEC = 0; DONE = 0;
        end
        Counterdec: begin
            SETCOCIENTE = 0; SETRESIDUO = 0; LD = 0; SHIFT = 0; DEC = 1; DONE = 0;
        end
        End: begin
            SETCOCIENTE = 0; SETRESIDUO = 0; LD = 0; SHIFT = 0; DEC = 0; DONE = 1;
        end
        default: begin
            SETCOCIENTE = 0; SETRESIDUO = 0; LD = 0; SHIFT = 0; DEC = 0; DONE = 0;
        end
    endcase
end

`ifdef BENCH
reg [8*20:1] estado_nombre;
always @(*) begin
    case (STATE)
        Start:      estado_nombre = "START";
        Check1:     estado_nombre = "CHECK1";
        Shift:      estado_nombre = "SHIFT";
        Check2:     estado_nombre = "CHECK2";
        Setco:      estado_nombre = "SETCO";
        Setcodi:    estado_nombre = "SETCODI";
        Counterdec: estado_nombre = "COUNTERDEC";
        End:        estado_nombre = "END";
        default:    estado_nombre = "unknown";
    endcase
end
`endif

endmodule

DEFINITIVOS/DIVISION/Control_TB.v
module Control_TB;
reg clk;
reg rst;
reg INIT;
reg ZERO;
reg RESIDUOCOMP;
wire SETCOCIENTE;
wire SETRESIDUO;
wire LD;
wire SHIFT;
wire DEC;
wire DONE;

Control uut (
    .clk(clk), .rst(rst), .INIT(INIT), .ZERO(ZERO), .RESIDUOCOMP(RESIDUOCOMP),
    .SETCOCIENTE(SETCOCIENTE), .SETRESIDUO(SETRESIDUO), .LD(LD),
    .SHIFT(SHIFT), .DEC(DEC), .DONE(DONE)
);

initial begin
    clk = 0;
    forever #20 clk = ~clk;
end

initial begin
    $dumpfile("Control_TB.vcd");
    $dumpvars(0, Control_TB);

    rst = 1; INIT = 0; ZERO = 0; RESIDUOCOMP = 0;
    @(posedge clk);
    rst = 0;

    @(posedge clk);
    INIT = 1;
    @(posedge clk);
    INIT = 0;
    @(posedge clk); // Check1 -> Shift (ZERO=0)
    @(posedge clk); // Shift -> Check2
    RESIDUOCOMP = 1;
    @(posedge clk); // Check2 -> Setcodi
    @(posedge clk); // Setcodi -> Counterdec
    @(posedge clk); // Counterdec -> Check1
    RESIDUOCOMP = 0;
    @(posedge clk); // Check1 -> Shift
    @(posedge clk); // Shift -> Check2
    @(posedge clk); // Check2 -> Setco
    @(posedge clk); // Setco -> Counterdec
    @(posedge clk); // Counterdec -> Check1
    ZERO = 1;
    @(posedge clk); // Check1 -> End
    @(posedge clk);
    #40;

    $finish;
end

endmodule

DEFINITIVOS/DIVISION/Control_TB.vcd
$date
	Mon Jul 13 13:24:48 2026
$end
$version
	Icarus Verilog
$end
$timescale
	1s
$end
$scope module Control_TB $end
$var wire 1 ! SHIFT $end
$var wire 1 " SETRESIDUO $end
$var wire 1 # SETCOCIENTE $end
$var wire 1 $ LD $end
$var wire 1 % DONE $end
$var wire 1 & DEC $end
$var reg 1 ' INIT $end
$var reg 1 ( RESIDUOCOMP $end
$var reg 1 ) ZERO $end
$var reg 1 * clk $end
$var reg 1 + rst $end
$scope module uut $end
$var wire 1 ' INIT $end
$var wire 1 ( RESIDUOCOMP $end
$var wire 1 ) ZERO $end
$var wire 1 * clk $end
$var wire 1 + rst $end
$var parameter 3 , Check1 $end
$var parameter 3 - Check2 $end
$var parameter 3 . Counterdec $end
$var parameter 3 / End $end
$var parameter 3 0 Setco $end
$var parameter 3 1 Setcodi $end
$var parameter 3 2 Shift $end
$var parameter 3 3 Start $end
$var reg 1 & DEC $end
$var reg 1 % DONE $end
$var reg 1 $ LD $end
$var reg 1 # SETCOCIENTE $end
$var reg 1 " SETRESIDUO $end
$var reg 1 ! SHIFT $end
$var reg 3 4 STATE [2:0] $end
$var reg 160 5 estado_nombre [160:1] $end
$upscope $end
$upscope $end
$enddefinitions $end
$comment Show the parameter values. $end
$dumpall
b0 3
b10 2
b101 1
b100 0
b111 /
b110 .
b11 -
b1 ,
$end
#0
$dumpvars
b101001101010100010000010101001001010100 5
b0 4
1+
0*
0)
0(
0'
0&
0%
1$
0#
0"
0!
$end
#20
0+
1*
#40
0*
#60
0$
b10000110100100001000101010000110100101100110001 5
b1 4
1'
1*
#80
0*
#100
b101001101001000010010010100011001010100 5
1!
b10 4
0'
1*
#120
0*
#140
0!
b10000110100100001000101010000110100101100110010 5
b11 4
1*
#160
0*
#180
b1010011010001010101010001000011010011110100010001001001 5
1"
1#
b101 4
1(
1*
#200
0*
#220
1&
0"
0#
b1000011010011110101010101001110010101000100010101010010010001000100010101000011 5
b110 4
1*
#240
0*
#260
b10000110100100001000101010000110100101100110001 5
0&
b1 4
1*
#280
0*
#300
1!
b101001101001000010010010100011001010100 5
b10 4
0(
1*
#320
0*
#340
b10000110100100001000101010000110100101100110010 5
0!
b11 4
1*
#360
0*
#380
b101001101000101010101000100001101001111 5
b100 4
1*
#400
0*
#420
b1000011010011110101010101001110010101000100010101010010010001000100010101000011 5
1&
b110 4
1*
#440
0*
#460
0&
b10000110100100001000101010000110100101100110001 5
b1 4
1*
#480
0*
#500
b10001010100111001000100 5
1%
b111 4
1)
1*
#520
0*
#540
0%
1$
b101001101010100010000010101001001010100 5
b0 4
1*
