DEFINITIVOS/DIVISION/Control.v
module Control (
    clk,
    rst,
    INIT,
    ZERO,
    RESIDUOCOMP,
    SETCOCIENTE,
    SETRESIDUO,
    LD,
    SHIFT,
    DEC,
    DONE
);
input clk;
input rst;
input INIT;
input ZERO;
input RESIDUOCOMP;
output reg SETCOCIENTE;
output reg SETRESIDUO;
output reg LD;
output reg SHIFT;
output reg DEC;
output reg DONE;

parameter Start      = 3'b000; // LD=1
parameter Check1     = 3'b001; // pregunta ZERO (C==0)
parameter Shift      = 3'b010; // (Residuo,Dividendo)<<1
parameter Check2     = 3'b011; // pregunta RESIDUOCOMP
parameter Setco      = 3'b100; // RESIDUOCOMP=0
parameter Setcodi    = 3'b101; // RESIDUOCOMP=1 -> SETCOCIENTE=1, SETRESIDUO=1
parameter Counterdec = 3'b110; // DEC=1
parameter End        = 3'b111; // DONE=1

reg [2:0] STATE;

always @(posedge clk or posedge rst) begin
    if (rst)
        STATE <= Start;
    else begin
        case (STATE)
            Start: begin
                if (INIT)
                    STATE <= Check1;
                else
                    STATE <= Start;
            end
            Check1: begin
                if (ZERO)
                    STATE <= End;
                else
                    STATE <= Shift;
            end
            Shift: begin
                STATE <= Check2;
            end
            Check2: begin
                if (RESIDUOCOMP)
                    STATE <= Setcodi;
                else
                    STATE <= Setco;
            end
            Setco: begin
                STATE <= Counterdec;
            end
            Setcodi: begin
                STATE <= Counterdec;
            end
            Counterdec: begin
                STATE <= Check1;
            end
            End: begin
                STATE <= Start;
            end
            default: STATE <= Start;
        endcase
    end
end

always @(*) begin
    case (STATE)
        Start: begin
            SETCOCIENTE = 0; SETRESIDUO = 0; LD = 1; SHIFT = 0; DEC = 0; DONE = 0;
        end
        Check1: begin
            SETCOCIENTE = 0; SETRESIDUO = 0; LD = 0; SHIFT = 0; DEC = 0; DONE = 0;
        end
        Shift: begin
            SETCOCIENTE = 0; SETRESIDUO = 0; LD = 0; SHIFT = 1; DEC = 0; DONE = 0;
        end
        Check2: begin
            SETCOCIENTE = 0; SETRESIDUO = 0; LD = 0; SHIFT = 0; DEC = 0; DONE = 0;
        end
        Setco: begin
            SETCOCIENTE = 0; SETRESIDUO = 0; LD = 0; SHIFT = 0; DEC = 0; DONE = 0;
        end
        Setcodi: begin
            SETCOCIENTE = 1; SETRESIDUO = 1; LD = 0; SHIFT = 0; DEC = 0; DONE = 0;
        end
        Counterdec: begin
            SETCOCIENTE = 0; SETRESIDUO = 0; LD = 0; SHIFT = 0; DEC = 1; DONE = 0;
        end
        End: begin
            SETCOCIENTE = 0; SETRESIDUO = 0; LD = 0; SHIFT = 0; DEC = 0; DONE = 1;
        end
        default: begin
            SETCOCIENTE = 0; SETRESIDUO = 0; LD = 0; SHIFT = 0; DEC = 0; DONE = 0;
        end
    endcase
end

`ifdef BENCH
reg [8*20:1] estado_nombre;
always @(*) begin
    case (STATE)
        Start:      estado_nombre = "START";
        Check1:     estado_nombre = "CHECK1";
        Shift:      estado_nombre = "SHIFT";
        Check2:     estado_nombre = "CHECK2";
        Setco:      estado_nombre = "SETCO";
        Setcodi:    estado_nombre = "SETCODI";
        Counterdec: estado_nombre = "COUNTERDEC";
        End:        estado_nombre = "END";
        default:    estado_nombre = "unknown";
    endcase
end
`endif

endmodule

DEFINITIVOS/DIVISION/Comp2.v
module Comp2 #(parameter CW = 4) (
    count,
    ZERO
);
input  [CW-1:0] count;
output ZERO;

assign ZERO = (count == {CW{1'b0}});

endmodule

DEFINITIVOS/DIVISION/Counter.v
module Counter #(parameter N = 8, parameter CW = 4) (
    clk,
    ld,
    Dec,
    count
);
input clk;
input ld;
input Dec;
output [CW-1:0] count;

reg [CW-1:0] cnt;
assign count = cnt;

always @(posedge clk) begin
    if (ld)
        cnt <= N[CW-1:0];
    else if (Dec)
        cnt <= cnt - 1'b1;
end

endmodule

DEFINITIVOS/DIVISION/Comp1.v
module Comp1 #(parameter N = 8) (
    Residuo,
    Divisor,
    RESIDUOCOMP
);
input [N:0]   Residuo;
input [N-1:0] Divisor;
output        RESIDUOCOMP;

assign RESIDUOCOMP = (Residuo >= {1'b0, Divisor}) ? 1'b1 : 1'b0;

endmodule

DEFINITIVOS/DIVISION/RegResiduo.v
module RegResiduo #(parameter N = 8) (
    clk,
    LD,
    SETRESIDUO,
    SHIFT,
    ShiftIn,
    DivisorComp,
    Residuo
);
input clk;
input LD;           
input SETRESIDUO;   
input SHIFT;        
input ShiftIn;       
input  [N:0] DivisorComp; 
output [N:0] Residuo;

reg [N:0] reg_residuo;
assign Residuo = reg_residuo;

always @(posedge clk) begin
    if (LD)
        reg_residuo <= {(N+1){1'b0}};
    else if (SETRESIDUO)
        reg_residuo <= reg_residuo + DivisorComp;
    else if (SHIFT)
        reg_residuo <= {reg_residuo[N-1:0], ShiftIn};
end

endmodule

DEFINITIVOS/DIVISION/Complement.v
module Complement #(parameter N = 8) (
    Divisor,
    DivisorComp
);
input  [N-1:0] Divisor;
output [N:0]   DivisorComp;

assign DivisorComp = (~{1'b0, Divisor}) + 1'b1;

endmodule

DEFINITIVOS/DIVISION/RegCociente.v
module RegCociente #(parameter N = 8) (
    clk,
    LD,
    SETCOCIENTE,
    SHIFT,
    Dividendo,
    Cociente,
    MSB
);

input clk;
input LD;            
input SETCOCIENTE;   
input SHIFT;         
input  [N-1:0] Dividendo;
output [N-1:0] Cociente;
output MSB;

reg [N-1:0] reg_cociente;
assign Cociente = reg_cociente;
assign MSB = reg_cociente[N-1];

always @(posedge clk) begin
    if (LD)
        reg_cociente <= Dividendo;
    else if (SETCOCIENTE)
        reg_cociente <= {reg_cociente[N-1:1], 1'b1};
    else if (SHIFT)
        reg_cociente <= {reg_cociente[N-2:0], 1'b0};
end

endmodule

DEFINITIVOS/DIVISION/CaminoDeDatos.v
module CaminoDeDatos #(parameter N = 8, parameter CW = 4) (
    clk,
    Divisor,
    Dividendo,
    LD,
    SETCOCIENTE,
    SETRESIDUO,
    SHIFT,
    DEC,
    RESIDUOCOMP,
    ZERO,
    Residuo,
    Cociente
);

input clk;
input [N-1:0] Divisor;
input [N-1:0] Dividendo;
input LD;
input SETCOCIENTE;
input SETRESIDUO;
input SHIFT;
input DEC;
output RESIDUOCOMP;
output ZERO;
output [N:0]   Residuo;
output [N-1:0] Cociente;

wire         cociente_msb;
wire [N:0]   divisorComp;
wire [CW-1:0] count;

RegCociente #(.N(N)) regCociente0 (
    .clk(clk),
    .LD(LD),
    .SETCOCIENTE(SETCOCIENTE),
    .SHIFT(SHIFT),
    .Dividendo(Dividendo),
    .Cociente(Cociente),
    .MSB(cociente_msb)
);

Complement #(.N(N)) complement0 (
    .Divisor(Divisor),
    .DivisorComp(divisorComp)
);

RegResiduo #(.N(N)) regResiduo0 (
    .clk(clk),
    .LD(LD),
    .SETRESIDUO(SETRESIDUO),
    .SHIFT(SHIFT),
    .ShiftIn(cociente_msb), // corrimiento combinado (Residuo,Dividendo)<<1
    .DivisorComp(divisorComp),
    .Residuo(Residuo)
);

Comp1 #(.N(N)) comp1_0 (
    .Residuo(Residuo),
    .Divisor(Divisor),
    .RESIDUOCOMP(RESIDUOCOMP)
);

Counter #(.N(N), .CW(CW)) counter0 (
    .clk(clk),
    .ld(LD),
    .Dec(DEC),
    .count(count)
);

Comp2 #(.CW(CW)) comp2_0 (
    .count(count),
    .ZERO(ZERO)
);

endmodule

DEFINITIVOS/DIVISION/Division.v
module Division #(parameter N = 8, parameter CW = 4) (
    clk,
    rst,
    INIT,
    Divisor,
    Dividendo,
    Residuo,
    Cociente,
    DONE
);
input clk;
input rst;
input INIT;
input  [N-1:0] Divisor;
input  [N-1:0] Dividendo;
output [N:0]   Residuo;
output [N-1:0] Cociente;
output DONE;

wire SETCOCIENTE;
wire SETRESIDUO;
wire LD;
wire SHIFT;
wire DEC;
wire RESIDUOCOMP;
wire ZERO;

CaminoDeDatos #(.N(N), .CW(CW)) caminoDeDatos0 (
    .clk(clk),
    .Divisor(Divisor),
    .Dividendo(Dividendo),
    .LD(LD),
    .SETCOCIENTE(SETCOCIENTE),
    .SETRESIDUO(SETRESIDUO),
    .SHIFT(SHIFT),
    .DEC(DEC),
    .RESIDUOCOMP(RESIDUOCOMP),
    .ZERO(ZERO),
    .Residuo(Residuo),
    .Cociente(Cociente)
);

Control control0 (
    .clk(clk),
    .rst(rst),
    .INIT(INIT),
    .ZERO(ZERO),
    .RESIDUOCOMP(RESIDUOCOMP),
    .SETCOCIENTE(SETCOCIENTE),
    .SETRESIDUO(SETRESIDUO),
    .LD(LD),
    .SHIFT(SHIFT),
    .DEC(DEC),
    .DONE(DONE)
);

endmodule

DEFINITIVOS/DIVISION/Division_TB.v
module Division_TB;
reg clk;
reg rst;
reg INIT;
reg [7:0] Divisor;
reg [7:0] Dividendo;
wire [8:0] Residuo;
wire [7:0] Cociente;
wire DONE;

Division #(.N(8), .CW(4)) uut (
    .clk(clk), .rst(rst), .INIT(INIT), .Divisor(Divisor), .Dividendo(Dividendo),
    .Residuo(Residuo), .Cociente(Cociente), .DONE(DONE)
);

initial begin
    clk = 0;
    forever #20 clk = ~clk;
end

task correr(input [7:0] dividendo_val, input [7:0] divisor_val);
    begin
        Dividendo = dividendo_val;
        Divisor = divisor_val;
        @(posedge clk); rst = 1;
        @(posedge clk); rst = 0; INIT = 1;
        @(posedge clk); INIT = 0;
        wait(DONE);
        #40;
    end
endtask

initial begin
    $dumpfile("Division_TB.vcd");
    $dumpvars(0, Division_TB);

    rst = 1; INIT = 0; Divisor = 0; Dividendo = 0;
    @(posedge clk); rst = 0; #40;

    correr(8'd20, 8'd5);
    correr(8'd7, 8'd2);
    correr(8'd255, 8'd3);
    correr(8'd100, 8'd7);
    correr(8'd0, 8'd9);
    correr(8'd9, 8'd200);

    $finish;
end

endmodule

DEFINITIVOS/DIVISION/Division_TB.vcd
$date
	Sat Jul 11 02:42:27 2026
$end
$version
	Icarus Verilog
$end
$timescale
	1s
$end
$scope module Division_TB $end
$var wire 9 ! Residuo [8:0] $end
$var wire 1 " DONE $end
$var wire 8 # Cociente [7:0] $end
$var reg 8 $ Dividendo [7:0] $end
$var reg 8 % Divisor [7:0] $end
$var reg 1 & INIT $end
$var reg 1 ' clk $end
$var reg 1 ( rst $end
$scope module uut $end
$var wire 8 ) Dividendo [7:0] $end
$var wire 8 * Divisor [7:0] $end
$var wire 1 & INIT $end
$var wire 1 ' clk $end
$var wire 1 ( rst $end
$var wire 1 + ZERO $end
$var wire 1 , SHIFT $end
$var wire 1 - SETRESIDUO $end
$var wire 1 . SETCOCIENTE $end
$var wire 9 / Residuo [8:0] $end
$var wire 1 0 RESIDUOCOMP $end
$var wire 1 1 LD $end
$var wire 1 " DONE $end
$var wire 1 2 DEC $end
$var wire 8 3 Cociente [7:0] $end
$var parameter 32 4 CW $end
$var parameter 32 5 N $end
$scope module caminoDeDatos0 $end
$var wire 8 6 Dividendo [7:0] $end
$var wire 8 7 Divisor [7:0] $end
$var wire 1 ' clk $end
$var wire 9 8 divisorComp [8:0] $end
$var wire 4 9 count [3:0] $end
$var wire 1 : cociente_msb $end
$var wire 1 + ZERO $end
$var wire 1 , SHIFT $end
$var wire 1 - SETRESIDUO $end
$var wire 1 . SETCOCIENTE $end
$var wire 9 ; Residuo [8:0] $end
$var wire 1 0 RESIDUOCOMP $end
$var wire 1 1 LD $end
$var wire 1 2 DEC $end
$var wire 8 < Cociente [7:0] $end
$var parameter 32 = CW $end
$var parameter 32 > N $end
$scope module comp1_0 $end
$var wire 8 ? Divisor [7:0] $end
$var wire 9 @ Residuo [8:0] $end
$var wire 1 0 RESIDUOCOMP $end
$var parameter 32 A N $end
$upscope $end
$scope module comp2_0 $end
$var wire 4 B count [3:0] $end
$var wire 1 + ZERO $end
$var parameter 32 C CW $end
$upscope $end
$scope module complement0 $end
$var wire 8 D Divisor [7:0] $end
$var wire 9 E DivisorComp [8:0] $end
$var parameter 32 F N $end
$upscope $end
$scope module counter0 $end
$var wire 1 ' clk $end
$var wire 4 G count [3:0] $end
$var wire 1 1 ld $end
$var wire 1 2 Dec $end
$var parameter 32 H CW $end
$var parameter 32 I N $end
$var reg 4 J cnt [3:0] $end
$upscope $end
$scope module regCociente0 $end
$var wire 8 K Cociente [7:0] $end
$var wire 8 L Dividendo [7:0] $end
$var wire 1 ' clk $end
$var wire 1 , SHIFT $end
$var wire 1 . SETCOCIENTE $end
$var wire 1 : MSB $end
$var wire 1 1 LD $end
$var parameter 32 M N $end
$var reg 8 N reg_cociente [7:0] $end
$upscope $end
$scope module regResiduo0 $end
$var wire 9 O DivisorComp [8:0] $end
$var wire 1 : ShiftIn $end
$var wire 1 ' clk $end
$var wire 1 , SHIFT $end
$var wire 1 - SETRESIDUO $end
$var wire 9 P Residuo [8:0] $end
$var wire 1 1 LD $end
$var parameter 32 Q N $end
$var reg 9 R reg_residuo [8:0] $end
$upscope $end
$upscope $end
$scope module control0 $end
$var wire 1 & INIT $end
$var wire 1 0 RESIDUOCOMP $end
$var wire 1 + ZERO $end
$var wire 1 ' clk $end
$var wire 1 ( rst $end
$var parameter 3 S Check1 $end
$var parameter 3 T Check2 $end
$var parameter 3 U Counterdec $end
$var parameter 3 V End $end
$var parameter 3 W Setco $end
$var parameter 3 X Setcodi $end
$var parameter 3 Y Shift $end
$var parameter 3 Z Start $end
$var reg 1 2 DEC $end
$var reg 1 " DONE $end
$var reg 1 1 LD $end
$var reg 1 . SETCOCIENTE $end
$var reg 1 - SETRESIDUO $end
$var reg 1 , SHIFT $end
$var reg 3 [ STATE [2:0] $end
$var reg 160 \ estado_nombre [160:1] $end
$upscope $end
$upscope $end
$scope task correr $end
$var reg 8 ] dividendo_val [7:0] $end
$var reg 8 ^ divisor_val [7:0] $end
$upscope $end
$upscope $end
$enddefinitions $end
$comment Show the parameter values. $end
$dumpall
b0 Z
b10 Y
b101 X
b100 W
b111 V
b110 U
b11 T
b1 S
b1000 Q
b1000 M
b1000 I
b100 H
b1000 F
b100 C
b1000 A
b1000 >
b100 =
b1000 5
b100 4
$end
#0
$dumpvars
bx ^
bx ]
b101001101010100010000010101001001010100 \
b0 [
bx R
bx P
b0 O
bx N
b0 L
bx K
bx J
bx G
b0 E
b0 D
bx B
bx @
b0 ?
bx <
bx ;
x:
bx 9
b0 8
b0 7
b0 6
bx 3
02
11
x0
bx /
0.
0-
0,
x+
b0 *
b0 )
1(
0'
0&
b0 %
b0 $
bx #
0"
bx !
$end
#20
0:
10
b0 #
b0 3
b0 <
b0 K
b0 N
b0 !
b0 /
b0 ;
b0 @
b0 P
b0 R
0+
b1000 9
b1000 B
b1000 G
b1000 J
0(
1'
#40
0'
#60
b10100 #
b10100 3
b10100 <
b10100 K
b10100 N
1(
00
b111111011 8
b111111011 E
b111111011 O
1'
b101 %
b101 *
b101 7
b101 ?
b101 D
b10100 $
b10100 )
b10100 6
b10100 L
b101 ^
b10100 ]
#80
0'
#100
01
b10000110100100001000101010000110100101100110001 \
b1 [
1&
0(
1'
#120
0'
#140
b101001101001000010010010100011001010100 \
1,
b10 [
0&
1'
#160
0'
#180
0,
b10000110100100001000101010000110100101100110010 \
b11 [
b101000 #
b101000 3
b101000 <
b101000 K
b101000 N
1'
#200
0'
#220
b101001101000101010101000100001101001111 \
b100 [
1'
#240
0'
#260
12
b1000011010011110101010101001110010101000100010101010010010001000100010101000011 \
b110 [
1'
#280
0'
#300
b10000110100100001000101010000110100101100110001 \
02
b1 [
b111 9
b111 B
b111 G
b111 J
1'
#320
0'
#340
1,
b101001101001000010010010100011001010100 \
b10 [
1'
#360
0'
#380
b10000110100100001000101010000110100101100110010 \
0,
b11 [
b1010000 #
b1010000 3
b1010000 <
b1010000 K
b1010000 N
1'
#400
0'
#420
b101001101000101010101000100001101001111 \
b100 [
1'
#440
0'
#460
b1000011010011110101010101001110010101000100010101010010010001000100010101000011 \
12
b110 [
1'
#480
0'
#500
02
b10000110100100001000101010000110100101100110001 \
b1 [
b110 9
b110 B
b110 G
b110 J
1'
#520
0'
#540
b101001101001000010010010100011001010100 \
1,
b10 [
1'
#560
0'
#580
0,
b10000110100100001000101010000110100101100110010 \
1:
b11 [
b10100000 #
b10100000 3
b10100000 <
b10100000 K
b10100000 N
1'
#600
0'
#620
b101001101000101010101000100001101001111 \
b100 [
1'
#640
0'
#660
12
b1000011010011110101010101001110010101000100010101010010010001000100010101000011 \
b110 [
1'
#680
0'
#700
b10000110100100001000101010000110100101100110001 \
02
b1 [
b101 9
b101 B
b101 G
b101 J
1'
#720
0'
#740
1,
b101001101001000010010010100011001010100 \
b10 [
1'
#760
0'
#780
b10000110100100001000101010000110100101100110010 \
0,
0:
b11 [
b1 !
b1 /
b1 ;
b1 @
b1 P
b1 R
b1000000 #
b1000000 3
b1000000 <
b1000000 K
b1000000 N
1'
#800
0'
#820
b101001101000101010101000100001101001111 \
b100 [
1'
#840
0'
#860
b1000011010011110101010101001110010101000100010101010010010001000100010101000011 \
12
b110 [
1'
#880
0'
#900
02
b10000110100100001000101010000110100101100110001 \
b1 [
b100 9
b100 B
b100 G
b100 J
1'
#920
0'
#940
b101001101001000010010010100011001010100 \
1,
b10 [
1'
#960
0'
#980
0,
b10000110100100001000101010000110100101100110010 \
1:
b11 [
b10000000 #
b10000000 3
b10000000 <
b10000000 K
b10000000 N
b10 !
b10 /
b10 ;
b10 @
b10 P
b10 R
1'
#1000
0'
#1020
b101001101000101010101000100001101001111 \
b100 [
1'
#1040
0'
#1060
12
b1000011010011110101010101001110010101000100010101010010010001000100010101000011 \
b110 [
1'
#1080
0'
#1100
b10000110100100001000101010000110100101100110001 \
02
b1 [
b11 9
b11 B
b11 G
b11 J
1'
#1120
0'
#1140
1,
b101001101001000010010010100011001010100 \
b10 [
1'
#1160
0'
#1180
b10000110100100001000101010000110100101100110010 \
0,
10
0:
b11 [
b101 !
b101 /
b101 ;
b101 @
b101 P
b101 R
b0 #
b0 3
b0 <
b0 K
b0 N
1'
#1200
0'
#1220
1-
1.
b1010011010001010101010001000011010011110100010001001001 \
b101 [
1'
#1240
0'
#1260
b1000011010011110101010101001110010101000100010101010010010001000100010101000011 \
12
0-
0.
00
b110 [
b0 !
b0 /
b0 ;
b0 @
b0 P
b0 R
b1 #
b1 3
b1 <
b1 K
b1 N
1'
#1280
0'
#1300
02
b10000110100100001000101010000110100101100110001 \
b1 [
b10 9
b10 B
b10 G
b10 J
1'
#1320
0'
#1340
b101001101001000010010010100011001010100 \
1,
b10 [
1'
#1360
0'
#1380
0,
b10000110100100001000101010000110100101100110010 \
b11 [
b10 #
b10 3
b10 <
b10 K
b10 N
1'
#1400
0'
#1420
b101001101000101010101000100001101001111 \
b100 [
1'
#1440
0'
#1460
12
b1000011010011110101010101001110010101000100010101010010010001000100010101000011 \
b110 [
1'
#1480
0'
#1500
b10000110100100001000101010000110100101100110001 \
02
b1 [
b1 9
b1 B
b1 G
b1 J
1'
#1520
0'
#1540
1,
b101001101001000010010010100011001010100 \
b10 [
1'
#1560
0'
#1580
b10000110100100001000101010000110100101100110010 \
0,
b11 [
b100 #
b100 3
b100 <
b100 K
b100 N
1'
#1600
0'
#1620
b101001101000101010101000100001101001111 \
b100 [
1'
#1640
0'
#1660
b1000011010011110101010101001110010101000100010101010010010001000100010101000011 \
12
b110 [
1'
#1680
0'
#1700
02
b10000110100100001000101010000110100101100110001 \
b1 [
1+
b0 9
b0 B
b0 G
b0 J
1'
#1720
0'
#1740
b10001010100111001000100 \
1"
b111 [
1'
#1760
0'
#1780
0"
11
b101001101010100010000010101001001010100 \
b0 [
1(
b111111110 8
b111111110 E
b111111110 O
1'
b10 %
b10 *
b10 7
b10 ?
b10 D
b111 $
b111 )
b111 6
b111 L
b10 ^
b111 ]
#1800
0'
#1820
b10000110100100001000101010000110100101100110001 \
01
b1 [
0+
b1000 9
b1000 B
b1000 G
b1000 J
b111 #
b111 3
b111 <
b111 K
b111 N
1&
0(
1'
#1840
0'
#1860
1,
b101001101001000010010010100011001010100 \
b10 [
0&
1'
#1880
0'
#1900
b10000110100100001000101010000110100101100110010 \
0,
b11 [
b1110 #
b1110 3
b1110 <
b1110 K
b1110 N
1'
#1920
0'
#1940
b101001101000101010101000100001101001111 \
b100 [
1'
#1960
0'
#1980
b1000011010011110101010101001110010101000100010101010010010001000100010101000011 \
12
b110 [
1'
#2000
0'
#2020
02
b10000110100100001000101010000110100101100110001 \
b1 [
b111 9
b111 B
b111 G
b111 J
1'
#2040
0'
#2060
b101001101001000010010010100011001010100 \
1,
b10 [
1'
#2080
0'
#2100
0,
b10000110100100001000101010000110100101100110010 \
b11 [
b11100 #
b11100 3
b11100 <
b11100 K
b11100 N
1'
#2120
0'
#2140
b101001101000101010101000100001101001111 \
b100 [
1'
#2160
0'
#2180
12
b1000011010011110101010101001110010101000100010101010010010001000100010101000011 \
b110 [
1'
#2200
0'
#2220
b10000110100100001000101010000110100101100110001 \
02
b1 [
b110 9
b110 B
b110 G
b110 J
1'
#2240
0'
#2260
1,
b101001101001000010010010100011001010100 \
b10 [
1'
#2280
0'
#2300
b10000110100100001000101010000110100101100110010 \
0,
b11 [
b111000 #
b111000 3
b111000 <
b111000 K
b111000 N
1'
#2320
0'
#2340
b101001101000101010101000100001101001111 \
b100 [
1'
#2360
0'
#2380
b1000011010011110101010101001110010101000100010101010010010001000100010101000011 \
12
b110 [
1'
#2400
0'
#2420
02
b10000110100100001000101010000110100101100110001 \
b1 [
b101 9
b101 B
b101 G
b101 J
1'
#2440
0'
#2460
b101001101001000010010010100011001010100 \
1,
b10 [
1'
#2480
0'
#2500
0,
b10000110100100001000101010000110100101100110010 \
b11 [
b1110000 #
b1110000 3
b1110000 <
b1110000 K
b1110000 N
1'
#2520
0'
#2540
b101001101000101010101000100001101001111 \
b100 [
1'
#2560
0'
#2580
12
b1000011010011110101010101001110010101000100010101010010010001000100010101000011 \
b110 [
1'
#2600
0'
#2620
b10000110100100001000101010000110100101100110001 \
02
b1 [
b100 9
b100 B
b100 G
b100 J
1'
#2640
0'
#2660
1,
b101001101001000010010010100011001010100 \
b10 [
1'
#2680
0'
#2700
b10000110100100001000101010000110100101100110010 \
0,
1:
b11 [
b11100000 #
b11100000 3
b11100000 <
b11100000 K
b11100000 N
1'
#2720
0'
#2740
b101001101000101010101000100001101001111 \
b100 [
1'
#2760
0'
#2780
b1000011010011110101010101001110010101000100010101010010010001000100010101000011 \
12
b110 [
1'
#2800
0'
#2820
02
b10000110100100001000101010000110100101100110001 \
b1 [
b11 9
b11 B
b11 G
b11 J
1'
#2840
0'
#2860
b101001101001000010010010100011001010100 \
1,
b10 [
1'
#2880
0'
#2900
0,
b10000110100100001000101010000110100101100110010 \
b11 [
b11000000 #
b11000000 3
b11000000 <
b11000000 K
b11000000 N
b1 !
b1 /
b1 ;
b1 @
b1 P
b1 R
1'
#2920
0'
#2940
b101001101000101010101000100001101001111 \
b100 [
1'
#2960
0'
#2980
12
b1000011010011110101010101001110010101000100010101010010010001000100010101000011 \
b110 [
1'
#3000
0'
#3020
b10000110100100001000101010000110100101100110001 \
02
b1 [
b10 9
b10 B
b10 G
b10 J
1'
#3040
0'
#3060
1,
b101001101001000010010010100011001010100 \
b10 [
1'
#3080
0'
#3100
b10000110100100001000101010000110100101100110010 \
0,
10
b11 [
b11 !
b11 /
b11 ;
b11 @
b11 P
b11 R
b10000000 #
b10000000 3
b10000000 <
b10000000 K
b10000000 N
1'
#3120
0'
#3140
1-
1.
b1010011010001010101010001000011010011110100010001001001 \
b101 [
1'
#3160
0'
#3180
b1000011010011110101010101001110010101000100010101010010010001000100010101000011 \
12
0-
0.
00
b110 [
b1 !
b1 /
b1 ;
b1 @
b1 P
b1 R
b10000001 #
b10000001 3
b10000001 <
b10000001 K
b10000001 N
1'
#3200
0'
#3220
02
b10000110100100001000101010000110100101100110001 \
b1 [
b1 9
b1 B
b1 G
b1 J
1'
#3240
0'
#3260
b101001101001000010010010100011001010100 \
1,
b10 [
1'
#3280
0'
#3300
0,
b10000110100100001000101010000110100101100110010 \
0:
10
b11 [
b10 #
b10 3
b10 <
b10 K
b10 N
b11 !
b11 /
b11 ;
b11 @
b11 P
b11 R
1'
#3320
0'
#3340
b1010011010001010101010001000011010011110100010001001001 \
1-
1.
b101 [
1'
#3360
0'
#3380
12
0-
0.
b1000011010011110101010101001110010101000100010101010010010001000100010101000011 \
00
b110 [
b11 #
b11 3
b11 <
b11 K
b11 N
b1 !
b1 /
b1 ;
b1 @
b1 P
b1 R
1'
#3400
0'
#3420
b10000110100100001000101010000110100101100110001 \
02
b1 [
1+
b0 9
b0 B
b0 G
b0 J
1'
#3440
0'
#3460
1"
b10001010100111001000100 \
b111 [
1'
#3480
0'
#3500
b101001101010100010000010101001001010100 \
0"
11
b0 [
1(
b111111101 8
b111111101 E
b111111101 O
1'
b11 %
b11 *
b11 7
b11 ?
b11 D
b11111111 $
b11111111 )
b11111111 6
b11111111 L
b11 ^
b11111111 ]
#3520
0'
#3540
01
b10000110100100001000101010000110100101100110001 \
1:
b1 [
b11111111 #
b11111111 3
b11111111 <
b11111111 K
b11111111 N
b0 !
b0 /
b0 ;
b0 @
b0 P
b0 R
0+
b1000 9
b1000 B
b1000 G
b1000 J
1&
0(
1'
#3560
0'
#3580
b101001101001000010010010100011001010100 \
1,
b10 [
0&
1'
#3600
0'
#3620
0,
b10000110100100001000101010000110100101100110010 \
b11 [
b11111110 #
b11111110 3
b11111110 <
b11111110 K
b11111110 N
b1 !
b1 /
b1 ;
b1 @
b1 P
b1 R
1'
#3640
0'
#3660
b101001101000101010101000100001101001111 \
b100 [
1'
#3680
0'
#3700
12
b1000011010011110101010101001110010101000100010101010010010001000100010101000011 \
b110 [
1'
#3720
0'
#3740
b10000110100100001000101010000110100101100110001 \
02
b1 [
b111 9
b111 B
b111 G
b111 J
1'
#3760
0'
#3780
1,
b101001101001000010010010100011001010100 \
b10 [
1'
#3800
0'
#3820
b10000110100100001000101010000110100101100110010 \
0,
10
b11 [
b11 !
b11 /
b11 ;
b11 @
b11 P
b11 R
b11111100 #
b11111100 3
b11111100 <
b11111100 K
b11111100 N
1'
#3840
0'
#3860
1-
1.
b1010011010001010101010001000011010011110100010001001001 \
b101 [
1'
#3880
0'
#3900
b1000011010011110101010101001110010101000100010101010010010001000100010101000011 \
12
0-
0.
00
b110 [
b0 !
b0 /
b0 ;
b0 @
b0 P
b0 R
b11111101 #
b11111101 3
b11111101 <
b11111101 K
b11111101 N
1'
#3920
0'
#3940
02
b10000110100100001000101010000110100101100110001 \
b1 [
b110 9
b110 B
b110 G
b110 J
1'
#3960
0'
#3980
b101001101001000010010010100011001010100 \
1,
b10 [
1'
#4000
0'
#4020
0,
b10000110100100001000101010000110100101100110010 \
b11 [
b11111010 #
b11111010 3
b11111010 <
b11111010 K
b11111010 N
b1 !
b1 /
b1 ;
b1 @
b1 P
b1 R
1'
#4040
0'
#4060
b101001101000101010101000100001101001111 \
b100 [
1'
#4080
0'
#4100
12
b1000011010011110101010101001110010101000100010101010010010001000100010101000011 \
b110 [
1'
#4120
0'
#4140
b10000110100100001000101010000110100101100110001 \
02
b1 [
b101 9
b101 B
b101 G
b101 J
1'
#4160
0'
#4180
1,
b101001101001000010010010100011001010100 \
b10 [
1'
#4200
0'
#4220
b10000110100100001000101010000110100101100110010 \
0,
10
b11 [
b11 !
b11 /
b11 ;
b11 @
b11 P
b11 R
b11110100 #
b11110100 3
b11110100 <
b11110100 K
b11110100 N
1'
#4240
0'
#4260
1-
1.
b1010011010001010101010001000011010011110100010001001001 \
b101 [
1'
#4280
0'
#4300
b1000011010011110101010101001110010101000100010101010010010001000100010101000011 \
12
0-
0.
00
b110 [
b0 !
b0 /
b0 ;
b0 @
b0 P
b0 R
b11110101 #
b11110101 3
b11110101 <
b11110101 K
b11110101 N
1'
#4320
0'
#4340
02
b10000110100100001000101010000110100101100110001 \
b1 [
b100 9
b100 B
b100 G
b100 J
1'
#4360
0'
#4380
b101001101001000010010010100011001010100 \
1,
b10 [
1'
#4400
0'
#4420
0,
b10000110100100001000101010000110100101100110010 \
b11 [
b11101010 #
b11101010 3
b11101010 <
b11101010 K
b11101010 N
b1 !
b1 /
b1 ;
b1 @
b1 P
b1 R
1'
#4440
0'
#4460
b101001101000101010101000100001101001111 \
b100 [
1'
#4480
0'
#4500
12
b1000011010011110101010101001110010101000100010101010010010001000100010101000011 \
b110 [
1'
#4520
0'
#4540
b10000110100100001000101010000110100101100110001 \
02
b1 [
b11 9
b11 B
b11 G
b11 J
1'
#4560
0'
#4580
1,
b101001101001000010010010100011001010100 \
b10 [
1'
#4600
0'
#4620
b10000110100100001000101010000110100101100110010 \
0,
10
b11 [
b11 !
b11 /
b11 ;
b11 @
b11 P
b11 R
b11010100 #
b11010100 3
b11010100 <
b11010100 K
b11010100 N
1'
#4640
0'
#4660
1-
1.
b1010011010001010101010001000011010011110100010001001001 \
b101 [
1'
#4680
0'
#4700
b1000011010011110101010101001110010101000100010101010010010001000100010101000011 \
12
0-
0.
00
b110 [
b0 !
b0 /
b0 ;
b0 @
b0 P
b0 R
b11010101 #
b11010101 3
b11010101 <
b11010101 K
b11010101 N
1'
#4720
0'
#4740
02
b10000110100100001000101010000110100101100110001 \
b1 [
b10 9
b10 B
b10 G
b10 J
1'
#4760
0'
#4780
b101001101001000010010010100011001010100 \
1,
b10 [
1'
#4800
0'
#4820
0,
b10000110100100001000101010000110100101100110010 \
b11 [
b10101010 #
b10101010 3
b10101010 <
b10101010 K
b10101010 N
b1 !
b1 /
b1 ;
b1 @
b1 P
b1 R
1'
#4840
0'
#4860
b101001101000101010101000100001101001111 \
b100 [
1'
#4880
0'
#4900
12
b1000011010011110101010101001110010101000100010101010010010001000100010101000011 \
b110 [
1'
#4920
0'
