DEFINITIVOS/BIN A BCD/Comp.v
module Comp(
    input [4:0] C,
    output ZERO
);

assign ZERO = (C == 5'd0);

endmodule

DEFINITIVOS/BIN A BCD/RegC.v
module RegC(
    input clk,
    input rst,
    input LD,
    input DEC,

    output reg [4:0] C
);

always @(posedge clk) begin
    if (rst)
        C <= 5'd16;

    else if (LD)
        C <= 5'd16;

    else if (DEC)
        C <= C - 1'b1;
end

endmodule

DEFINITIVOS/BIN A BCD/CorreccionBCD.v
module CorreccionBCD(
    input [35:0] Bin,
    output reg [19:0] BCDCorregido
);

always @(*) begin

    BCDCorregido = Bin[35:16];

    if (BCDCorregido[3:0] >= 5)
        BCDCorregido[3:0] =
            BCDCorregido[3:0] + 3;

    if (BCDCorregido[7:4] >= 5)
        BCDCorregido[7:4] =
            BCDCorregido[7:4] + 3;

    if (BCDCorregido[11:8] >= 5)
        BCDCorregido[11:8] =
            BCDCorregido[11:8] + 3;

    if (BCDCorregido[15:12] >= 5)
        BCDCorregido[15:12] =
            BCDCorregido[15:12] + 3;

    if (BCDCorregido[19:16] >= 5)
        BCDCorregido[19:16] =
            BCDCorregido[19:16] + 3;

end

endmodule

DEFINITIVOS/BIN A BCD/RegBin.v
module RegBin(
    input clk,
    input rst,
    input ADD,
    input SHIFT,
    input LD,
    input [15:0] Binario,
    input [19:0] BCDCorregido,

    output reg [35:0] Bin
);

always @(posedge clk) begin
    if (rst)
        Bin <= 36'b0;

    else if (LD)
        Bin <= {20'b0, Binario};

    else if (ADD)
        Bin[35:16] <= BCDCorregido;

    else if (SHIFT)
        Bin <= Bin << 1;
end

endmodule

DEFINITIVOS/BIN A BCD/CaminoDeDatos.v
module CaminoDeDatos(
    input clk,
    input rst,
    input ADD,
    input LD,
    input SHIFT,
    input DEC,
    input [15:0] Binario,

    output [19:0] BCD,
    output ZERO
);

wire [35:0] Bin;
wire [19:0] BCDCorregido;
wire [4:0] C;

RegBin REGBIN(
    .clk(clk),
    .rst(rst),
    .ADD(ADD),
    .SHIFT(SHIFT),
    .LD(LD),
    .Binario(Binario),
    .BCDCorregido(BCDCorregido),
    .Bin(Bin)
);

CorreccionBCD CORRECCION(
    .Bin(Bin),
    .BCDCorregido(BCDCorregido)
);

RegC REGC(
    .clk(clk),
    .rst(rst),
    .LD(LD),
    .DEC(DEC),
    .C(C)
);

Comp COMPARADOR(
    .C(C),
    .ZERO(ZERO)
);

assign BCD = Bin[35:16];

endmodule

DEFINITIVOS/BIN A BCD/Control.v
module Control(
    input clk,
    input rst,
    input INIT,
    input ZERO,

    output reg ADD,
    output reg LD,
    output reg SHIFT,
    output reg DEC,
    output reg DONE
);

reg [2:0] Estado;

parameter START    = 3'd0;
parameter CHECK1   = 3'd1;
parameter CHECK2   = 3'd2;
parameter ADDSTATE = 3'd3;
parameter SHIFTDEC = 3'd4;
parameter FINAL    = 3'd5;

always @(posedge clk) begin
    if (rst)
        Estado <= START;
    else begin
        case (Estado)

            START:
                if (INIT)
                    Estado <= CHECK1;
                else
                    Estado <= START;

            CHECK1:
                if (ZERO)
                    Estado <= FINAL;
                else
                    Estado <= CHECK2;

            CHECK2:
                Estado <= ADDSTATE;

            ADDSTATE:
                Estado <= SHIFTDEC;

            SHIFTDEC:
                Estado <= CHECK1;

            FINAL:
                Estado <= START;

            default:
                Estado <= START;

        endcase
    end
end

always @(*) begin
    case (Estado)

        START: begin
            ADD   = 0;
            LD    = 1;
            SHIFT = 0;
            DEC   = 0;
            DONE  = 0;
        end

        CHECK1: begin
            ADD   = 0;
            LD    = 0;
            SHIFT = 0;
            DEC   = 0;
            DONE  = 0;
        end

        CHECK2: begin
            ADD   = 0;
            LD    = 0;
            SHIFT = 0;
            DEC   = 0;
            DONE  = 0;
        end

        ADDSTATE: begin
            ADD   = 1;
            LD    = 0;
            SHIFT = 0;
            DEC   = 0;
            DONE  = 0;
        end

        SHIFTDEC: begin
            ADD   = 0;
            LD    = 0;
            SHIFT = 1;
            DEC   = 1;
            DONE  = 0;
        end

        FINAL: begin
            ADD   = 0;
            LD    = 0;
            SHIFT = 0;
            DEC   = 0;
            DONE  = 1;
        end

        default: begin
            ADD   = 0;
            LD    = 0;
            SHIFT = 0;
            DEC   = 0;
            DONE  = 0;
        end

    endcase
end

endmodule

DEFINITIVOS/BIN A BCD/ConversorBCD.v
module ConversorBCD(
    input clk,
    input rst,
    input INIT,
    input [15:0] Binario,

    output [19:0] BCD,
    output DONE
);

wire ADD;
wire LD;
wire SHIFT;
wire DEC;
wire ZERO;

Control CONTROL(
    .clk(clk),
    .rst(rst),
    .INIT(INIT),
    .ZERO(ZERO),
    .ADD(ADD),
    .LD(LD),
    .SHIFT(SHIFT),
    .DEC(DEC),
    .DONE(DONE)
);

CaminoDeDatos DATOS(
    .clk(clk),
    .rst(rst),
    .ADD(ADD),
    .LD(LD),
    .SHIFT(SHIFT),
    .DEC(DEC),
    .Binario(Binario),
    .BCD(BCD),
    .ZERO(ZERO)
);

endmodule

DEFINITIVOS/BIN A BCD/ConversorBCD_TB.v
module ConversorBCD_TB;

reg clk;
reg rst;
reg INIT;
reg [15:0] Binario;

wire [19:0] BCD;
wire DONE;

ConversorBCD uut(
    .clk(clk),
    .rst(rst),
    .INIT(INIT),
    .Binario(Binario),
    .BCD(BCD),
    .DONE(DONE)
);

initial begin
    clk = 0;
    forever #20 clk = ~clk;
end

task prueba;
input [15:0] numero;
begin
    rst = 1;
    INIT = 0;
    Binario = numero;

    @(posedge clk);
    rst = 0;
    INIT = 1;

    @(posedge clk);
    INIT = 0;

    wait(DONE);

    #40;
end
endtask

initial begin
    $dumpfile("ConversorBCD_TB.vcd");
    $dumpvars(0, ConversorBCD_TB);

    prueba(0);
    prueba(9);
    prueba(25);
    prueba(1234);
    prueba(12345);
    prueba(65535);

    $finish;
end

endmodule

DEFINITIVOS/BIN A BCD/ConversorBCD_TB.vcd
$date
	Mon Jul 13 13:49:54 2026
$end
$version
	Icarus Verilog
$end
$timescale
	1s
$end
$scope module ConversorBCD_TB $end
$var wire 1 ! DONE $end
$var wire 20 " BCD [19:0] $end
$var reg 16 # Binario [15:0] $end
$var reg 1 $ INIT $end
$var reg 1 % clk $end
$var reg 1 & rst $end
$scope module uut $end
$var wire 16 ' Binario [15:0] $end
$var wire 1 $ INIT $end
$var wire 1 % clk $end
$var wire 1 & rst $end
$var wire 1 ( ZERO $end
$var wire 1 ) SHIFT $end
$var wire 1 * LD $end
$var wire 1 ! DONE $end
$var wire 1 + DEC $end
$var wire 20 , BCD [19:0] $end
$var wire 1 - ADD $end
$scope module CONTROL $end
$var wire 1 $ INIT $end
$var wire 1 % clk $end
$var wire 1 & rst $end
$var wire 1 ( ZERO $end
$var parameter 3 . ADDSTATE $end
$var parameter 3 / CHECK1 $end
$var parameter 3 0 CHECK2 $end
$var parameter 3 1 FINAL $end
$var parameter 3 2 SHIFTDEC $end
$var parameter 3 3 START $end
$var reg 1 - ADD $end
$var reg 1 + DEC $end
$var reg 1 ! DONE $end
$var reg 3 4 Estado [2:0] $end
$var reg 1 * LD $end
$var reg 1 ) SHIFT $end
$upscope $end
$scope module DATOS $end
$var wire 1 - ADD $end
$var wire 16 5 Binario [15:0] $end
$var wire 1 + DEC $end
$var wire 1 * LD $end
$var wire 1 ) SHIFT $end
$var wire 1 % clk $end
$var wire 1 & rst $end
$var wire 1 ( ZERO $end
$var wire 5 6 C [4:0] $end
$var wire 36 7 Bin [35:0] $end
$var wire 20 8 BCDCorregido [19:0] $end
$var wire 20 9 BCD [19:0] $end
$scope module COMPARADOR $end
$var wire 1 ( ZERO $end
$var wire 5 : C [4:0] $end
$upscope $end
$scope module CORRECCION $end
$var wire 36 ; Bin [35:0] $end
$var reg 20 < BCDCorregido [19:0] $end
$upscope $end
$scope module REGBIN $end
$var wire 1 - ADD $end
$var wire 20 = BCDCorregido [19:0] $end
$var wire 16 > Binario [15:0] $end
$var wire 1 * LD $end
$var wire 1 ) SHIFT $end
$var wire 1 % clk $end
$var wire 1 & rst $end
$var reg 36 ? Bin [35:0] $end
$upscope $end
$scope module REGC $end
$var wire 1 + DEC $end
$var wire 1 * LD $end
$var wire 1 % clk $end
$var wire 1 & rst $end
$var reg 5 @ C [4:0] $end
$upscope $end
$upscope $end
$upscope $end
$scope task prueba $end
$var reg 16 A numero [15:0] $end
$upscope $end
$upscope $end
$enddefinitions $end
$comment Show the parameter values. $end
$dumpall
b0 3
b100 2
b101 1
b10 0
b1 /
b11 .
$end
#0
$dumpvars
b0 A
bx @
bx ?
b0 >
bx =
bx <
bx ;
bx :
bx 9
bx 8
bx 7
bx 6
b0 5
bx 4
x-
bx ,
x+
x*
x)
x(
b0 '
1&
0%
0$
b0 #
bx "
x!
$end
#20
0!
0+
0)
1*
0-
b0 4
1$
0&
1%
#40
0%
#60
b0 "
b0 ,
b0 9
b0 8
b0 <
b0 =
0*
0(
b10000 6
b10000 :
b10000 @
b0 7
b0 ;
b0 ?
b1 4
0$
1%
#80
0%
#100
b10 4
1%
#120
0%
#140
1-
b11 4
1%
#160
0%
#180
1+
1)
0-
b100 4
1%
#200
0%
#220
0+
0)
b1111 6
b1111 :
b1111 @
b1 4
1%
#240
0%
#260
b10 4
1%
#280
0%
#300
1-
b11 4
1%
#320
0%
#340
1+
1)
0-
b100 4
1%
#360
0%
#380
0+
0)
b1110 6
b1110 :
b1110 @
b1 4
1%
#400
0%
#420
b10 4
1%
#440
0%
#460
1-
b11 4
1%
#480
0%
#500
1+
1)
0-
b100 4
1%
#520
0%
#540
0+
0)
b1101 6
b1101 :
b1101 @
b1 4
1%
#560
0%
#580
b10 4
1%
#600
0%
#620
1-
b11 4
1%
#640
0%
#660
1+
1)
0-
b100 4
1%
#680
0%
#700
0+
0)
b1100 6
b1100 :
b1100 @
b1 4
1%
#720
0%
#740
b10 4
1%
#760
0%
#780
1-
b11 4
1%
#800
0%
#820
1+
1)
0-
b100 4
1%
#840
0%
#860
0+
0)
b1011 6
b1011 :
b1011 @
b1 4
1%
#880
0%
#900
b10 4
1%
#920
0%
#940
1-
b11 4
1%
#960
0%
#980
1+
1)
0-
b100 4
1%
#1000
0%
#1020
0+
0)
b1010 6
b1010 :
b1010 @
b1 4
1%
#1040
0%
#1060
b10 4
1%
#1080
0%
#1100
1-
b11 4
1%
#1120
0%
#1140
1+
1)
0-
b100 4
1%
#1160
0%
#1180
0+
0)
b1001 6
b1001 :
b1001 @
b1 4
1%
#1200
0%
#1220
b10 4
1%
#1240
0%
#1260
1-
b11 4
1%
#1280
0%
#1300
1+
1)
0-
b100 4
1%
#1320
0%
#1340
0+
0)
b1000 6
b1000 :
b1000 @
b1 4
1%
#1360
0%
#1380
b10 4
1%
#1400
0%
#1420
1-
b11 4
1%
#1440
0%
#1460
1+
1)
0-
b100 4
1%
#1480
0%
#1500
0+
0)
b111 6
b111 :
b111 @
b1 4
1%
#1520
0%
#1540
b10 4
1%
#1560
0%
#1580
1-
b11 4
1%
#1600
0%
#1620
1+
1)
0-
b100 4
1%
#1640
0%
#1660
0+
0)
b110 6
b110 :
b110 @
b1 4
1%
#1680
0%
#1700
b10 4
1%
#1720
0%
#1740
1-
b11 4
1%
#1760
0%
#1780
1+
1)
0-
b100 4
1%
#1800
0%
#1820
0+
0)
b101 6
b101 :
b101 @
b1 4
1%
#1840
0%
#1860
b10 4
1%
#1880
0%
#1900
1-
b11 4
1%
#1920
0%
#1940
1+
1)
0-
b100 4
1%
#1960
0%
#1980
0+
0)
b100 6
b100 :
b100 @
b1 4
1%
#2000
0%
#2020
b10 4
1%
#2040
0%
#2060
1-
b11 4
1%
#2080
0%
#2100
1+
1)
0-
b100 4
1%
#2120
0%
#2140
0+
0)
b11 6
b11 :
b11 @
b1 4
1%
#2160
0%
#2180
b10 4
1%
#2200
0%
#2220
1-
b11 4
1%
#2240
0%
#2260
1+
1)
0-
b100 4
1%
#2280
0%
#2300
0+
0)
b10 6
b10 :
b10 @
b1 4
1%
#2320
0%
#2340
b10 4
1%
#2360
0%
#2380
1-
b11 4
1%
#2400
0%
#2420
1+
1)
0-
b100 4
1%
#2440
0%
#2460
0+
0)
b1 6
b1 :
b1 @
b1 4
1%
#2480
0%
#2500
b10 4
1%
#2520
0%
#2540
1-
b11 4
1%
#2560
0%
#2580
1+
1)
0-
b100 4
1%
#2600
0%
#2620
0+
0)
1(
b0 6
b0 :
b0 @
b1 4
1%
#2640
0%
#2660
1!
b101 4
1%
#2680
0%
#2700
0!
1*
b0 4
1$
1%
b1001 #
b1001 '
b1001 5
b1001 >
0&
b1001 A
#2720
0%
#2740
0*
b1 4
b1001 7
b1001 ;
b1001 ?
0(
b10000 6
b10000 :
b10000 @
0$
1%
#2760
0%
#2780
b10 4
1%
#2800
0%
#2820
1-
b11 4
1%
#2840
0%
#2860
1+
1)
0-
b100 4
1%
#2880
0%
#2900
0+
0)
b1 4
b10010 7
b10010 ;
b10010 ?
b1111 6
b1111 :
b1111 @
1%
#2920
0%
#2940
b10 4
1%
#2960
0%
#2980
1-
b11 4
1%
#3000
0%
#3020
1+
1)
0-
b100 4
1%
#3040
0%
#3060
0+
0)
b1 4
b100100 7
b100100 ;
b100100 ?
b1110 6
b1110 :
b1110 @
1%
#3080
0%
#3100
b10 4
1%
#3120
0%
#3140
1-
b11 4
1%
#3160
0%
#3180
1+
1)
0-
b100 4
1%
#3200
0%
#3220
0+
0)
b1 4
b1001000 7
b1001000 ;
b1001000 ?
b1101 6
b1101 :
b1101 @
1%
#3240
0%
#3260
b10 4
1%
#3280
0%
#3300
1-
b11 4
1%
#3320
0%
#3340
1+
1)
0-
b100 4
1%
#3360
0%
#3380
0+
0)
b1 4
b10010000 7
b10010000 ;
b10010000 ?
b1100 6
b1100 :
b1100 @
1%
#3400
0%
#3420
b10 4
1%
#3440
0%
#3460
1-
b11 4
1%
#3480
0%
#3500
1+
1)
0-
b100 4
1%
#3520
0%
#3540
0+
0)
b1 4
b100100000 7
b100100000 ;
b100100000 ?
b1011 6
b1011 :
b1011 @
1%
#3560
0%
#3580
b10 4
1%
#3600
0%
#3620
1-
b11 4
1%
#3640
0%
#3660
1+
1)
0-
b100 4
1%
#3680
0%
#3700
0+
0)
b1 4
b1001000000 7
b1001000000 ;
b1001000000 ?
b1010 6
b1010 :
b1010 @
1%
#3720
0%
#3740
b10 4
1%
#3760
0%
#3780
1-
b11 4
1%
#3800
0%
#3820
1+
1)
0-
b100 4
1%
#3840
0%
#3860
0+
0)
b1 4
b10010000000 7
b10010000000 ;
b10010000000 ?
b1001 6
b1001 :
b1001 @
1%
#3880
0%
#3900
b10 4
1%
#3920
0%
#3940
1-
b11 4
1%
#3960
0%
#3980
1+
1)
0-
b100 4
1%
#4000
0%
#4020
0+
0)
b1 4
b100100000000 7
b100100000000 ;
b100100000000 ?
b1000 6
b1000 :
b1000 @
1%
#4040
0%
#4060
b10 4
1%
#4080
0%
#4100
1-
b11 4
1%
#4120
0%
#4140
1+
1)
0-
b100 4
1%
#4160
0%
#4180
0+
0)
b1 4
b1001000000000 7
b1001000000000 ;
b1001000000000 ?
b111 6
b111 :
b111 @
1%
#4200
0%
#4220
b10 4
1%
#4240
0%
#4260
1-
b11 4
1%
#4280
0%
#4300
1+
1)
0-
b100 4
1%
#4320
0%
#4340
0+
0)
b1 4
b10010000000000 7
b10010000000000 ;
b10010000000000 ?
b110 6
b110 :
b110 @
1%
#4360
0%
#4380
b10 4
1%
#4400
0%
#4420
1-
b11 4
1%
#4440
0%
#4460
1+
1)
0-
b100 4
1%
#4480
0%
#4500
0+
0)
b1 4
b100100000000000 7
b100100000000000 ;
b100100000000000 ?
b101 6
b101 :
b101 @
1%
#4520
0%
#4540
b10 4
1%
#4560
0%
#4580
1-
b11 4
1%
#4600
0%
#4620
1+
1)
0-
b100 4
1%
#4640
0%
#4660
0+
0)
b1 4
b1001000000000000 7
b1001000000000000 ;
b1001000000000000 ?
b100 6
b100 :
b100 @
1%
#4680
0%
#4700
b10 4
1%
#4720
0%
#4740
1-
b11 4
1%
#4760
0%
#4780
1+
1)
0-
b100 4
1%
#4800
0%
#4820
0+
0)
b1 "
b1 ,
b1 9
b1 8
b1 <
b1 =
b1 4
b10010000000000000 7
b10010000000000000 ;
b10010000000000000 ?
b11 6
b11 :
b11 @
1%
#4840
0%
#4860
b10 4
1%
#4880
0%
#4900
1-
b11 4
1%
#4920
0%
#4940
1+
1)
0-
b100 4
1%
#4960
0%
#4980
0+
0)
b10 "
b10 ,
b10 9
b10 8
b10 <
b10 =
b1 4
b100100000000000000 7
b100100000000000000 ;
b100100000000000000 ?
b10 6
b10 :
b10 @
1%
#5000
0%
#5020
b10 4
1%
#5040
0%
#5060
1-
b11 4
1%
#5080
0%
#5100
1+
1)
0-
b100 4
1%
#5120
0%
#5140
0+
0)
b100 "
b100 ,
b100 9
b100 8
b100 <
b100 =
b1 4
b1001000000000000000 7
b1001000000000000000 ;
b1001000000000000000 ?
b1 6
b1 :
b1 @
1%
#5160
0%
#5180
b10 4
1%
#5200
0%
#5220
1-
b11 4
1%
#5240
0%
#5260
1+
1)
0-
b100 4
1%
#5280
0%
#5300
0+
0)
b1001 "
b1001 ,
b1001 9
b1100 8
b1100 <
b1100 =
b1 4
b10010000000000000000 7
b10010000000000000000 ;
b10010000000000000000 ?
1(
b0 6
b0 :
b0 @
1%
#5320
0%
#5340
1!
b101 4
1%
#5360
0%
#5380
0!
1*
b0 4
1$
1%
b11001 #
b11001 '
b11001 5
b11001 >
0&
b11001 A
#5400
0%
#5420
b0 "
b0 ,
b0 9
b0 8
b0 <
b0 =
0*
0(
b10000 6
b10000 :
b10000 @
b11001 7
b11001 ;
b11001 ?
b1 4
0$
1%
#5440
0%
#5460
b10 4
1%
#5480
0%
#5500
1-
b11 4
1%
#5520
0%
#5540
1+
1)
0-
b100 4
1%
#5560
0%
#5580
0+
0)
b1111 6
b1111 :
b1111 @
b110010 7
b110010 ;
b110010 ?
b1 4
1%
#5600
0%
#5620
b10 4
1%
#5640
0%
#5660
1-
b11 4
1%
#5680
0%
#5700
1+
1)
0-
b100 4
1%
#5720
0%
#5740
0+
0)
b1110 6
b1110 :
b1110 @
b1100100 7
b1100100 ;
b1100100 ?
b1 4
1%
#5760
0%
#5780
b10 4
1%
#5800
0%
#5820
1-
b11 4
1%
#5840
0%
#5860
1+
1)
0-
b100 4
1%
#5880
0%
#5900
0+
0)
b1101 6
b1101 :
b1101 @
b11001000 7
b11001000 ;
b11001000 ?
b1 4
1%
#5920
0%
#5940
b10 4
1%
#5960
0%
#5980
1-
b11 4
1%
#6000
0%
#6020
1+
1)
0-
b100 4
1%
#6040
0%
#6060
0+
0)
b1100 6
b1100 :
b1100 @
b110010000 7
b110010000 ;
b110010000 ?
b1 4
1%
#6080
0%
#6100
b10 4
1%
#6120
0%
#6140
1-
b11 4
1%
#6160
0%
#6180
1+
1)
0-
b100 4
1%
#6200
0%
#6220
0+
0)
b1011 6
b1011 :
b1011 @
b1100100000 7
b1100100000 ;
b1100100000 ?
b1 4
1%
#6240
0%
#6260
b10 4
1%
#6280
0%
#6300
1-
b11 4
1%
#6320
0%
#6340
1+
1)
0-
b100 4
1%
#6360
0%
#6380
0+
0)
b1010 6
b1010 :
b1010 @
b11001000000 7
b11001000000 ;
b11001000000 ?
b1 4
1%
#6400
0%
#6420
b10 4
1%
#6440
0%
#6460
1-
b11 4
1%
#6480
0%
#6500
1+
1)
0-
b100 4
1%
#6520
0%
#6540
0+
0)
b1001 6
b1001 :
b1001 @
b110010000000 7
b110010000000 ;
b110010000000 ?
b1 4
1%
#6560
0%
#6580
b10 4
1%
#6600
0%
#6620
1-
b11 4
1%
#6640
0%
#6660
1+
1)
0-
b100 4
1%
#6680
0%
#6700
0+
0)
b1000 6
b1000 :
b1000 @
b1100100000000 7
b1100100000000 ;
b1100100000000 ?
b1 4
1%
#6720
0%
#6740
b10 4
1%
#6760
0%
#6780
1-
b11 4
1%
#6800
0%
#6820
1+
1)
0-
b100 4
1%
#6840
0%
#6860
0+
0)
b111 6
b111 :
b111 @
b11001000000000 7
b11001000000000 ;
b11001000000000 ?
b1 4
1%
#6880
0%
#6900
b10 4
1%
#6920
0%
#6940
1-
b11 4
1%
#6960
0%
#6980
1+
1)
0-
b100 4
1%
#7000
0%
#7020
0+
0)
b110 6
b110 :
b110 @
b110010000000000 7
b110010000000000 ;
b110010000000000 ?
b1 4
1%
#7040
0%
#7060
b10 4
1%
#7080
0%
#7100
1-
b11 4
1%
#7120
0%
#7140
1+
1)
0-
b100 4
1%
#7160
0%
#7180
0+
0)
b101 6
b101 :
b101 @
b1100100000000000 7
b1100100000000000 ;
b1100100000000000 ?
b1 4
1%
#7200
0%
#7220
b10 4
1%
#7240
0%
#7260
1-
b11 4
1%
#7280
0%
#7300
1+
1)
0-
b100 4
1%
#7320
0%
#7340
b1 "
b1 ,
b1 9
b1 8
b1 <
b1 =
0+
0)
b100 6
b100 :
b100 @
b11001000000000000 7
b11001000000000000 ;
b11001000000000000 ?
b1 4
1%
#7360
0%
#7380
b10 4
1%
#7400
0%
#7420
1-
b11 4
1%
#7440
0%
#7460
1+
1)
0-
b100 4
1%
#7480
0%
#7500
b11 "
b11 ,
b11 9
b11 8
b11 <
b11 =
0+
0)
b11 6
b11 :
b11 @
b110010000000000000 7
b110010000000000000 ;
b110010000000000000 ?
b1 4
1%
#7520
0%
#7540
b10 4
1%
#7560
0%
#7580
1-
b11 4
1%
#7600
0%
#7620
1+
1)
0-
b100 4
1%
#7640
0%
#7660
b110 "
b110 ,
b110 9
b1001 8
b1001 <
b1001 =
0+
0)
b10 6
b10 :
b10 @
b1100100000000000000 7
b1100100000000000000 ;
b1100100000000000000 ?
b1 4
1%
#7680
0%
#7700
b10 4
1%
#7720
0%
#7740
1-
b11 4
1%
#7760
0%
#7780
1+
1)
0-
b1001 "
b1001 ,
b1001 9
b1100 8
b1100 <
b1100 =
b100 4
b10010100000000000000 7
b10010100000000000000 ;
b10010100000000000000 ?
1%
#7800
0%
#7820
b10010 "
b10010 ,
b10010 9
b10010 8
b10010 <
b10010 =
0+
0)
b1 6
b1 :
b1 @
b100101000000000000000 7
b100101000000000000000 ;
b100101000000000000000 ?
b1 4
1%
#7840
0%
#7860
b10 4
1%
#7880
0%
#7900
1-
b11 4
1%
#7920
0%
#7940
1+
1)
0-
b100 4
1%
#7960
0%
#7980
b100101 "
b100101 ,
b100101 9
b101000 8
b101000 <
b101000 =
0+
0)
1(
b0 6
b0 :
b0 @
b1001010000000000000000 7
b1001010000000000000000 ;
b1001010000000000000000 ?
b1 4
1%
#8000
0%
#8020
1!
b101 4
1%
#8040
0%
#8060
0!
1*
b0 4
1$
1%
b10011010010 #
b10011010010 '
b10011010010 5
b10011010010 >
0&
b10011010010 A
#8080
0%
#8100
0*
b0 "
b0 ,
b0 9
b0 8
b0 <
b0 =
b1 4
b10011010010 7
b10011010010 ;
b10011010010 ?
0(
b10000 6
b10000 :
b10000 @
0$
1%
#8120
0%
#8140
b10 4
1%
#8160
0%
#8180
1-
b11 4
1%
#8200
0%
#8220
1+
1)
0-
b100 4
1%
#8240
0%
#8260
0+
0)
b1 4
b100110100100 7
b100110100100 ;
b100110100100 ?
b1111 6
b1111 :
b1111 @
1%
#8280
0%
#8300
b10 4
1%
#8320
0%
#8340
1-
b11 4
1%
#8360
0%
#8380
1+
1)
0-
b100 4
1%
#8400
0%
#8420
0+
0)
b1 4
b1001101001000 7
b1001101001000 ;
b1001101001000 ?
b1110 6
b1110 :
b1110 @
1%
#8440
0%
#8460
b10 4
1%
#8480
0%
#8500
1-
b11 4
1%
#8520
0%
#8540
1+
1)
0-
b100 4
1%
#8560
0%
#8580
0+
0)
b1 4
b10011010010000 7
b10011010010000 ;
b10011010010000 ?
b1101 6
b1101 :
b1101 @
1%
#8600
0%
#8620
b10 4
1%
#8640
0%
#8660
1-
b11 4
1%
#8680
0%
#8700
1+
1)
0-
b100 4
1%
#8720
0%
#8740
0+
0)
b1 4
b100110100100000 7
b100110100100000 ;
b100110100100000 ?
b1100 6
b1100 :
b1100 @
1%
#8760
0%
#8780
b10 4
1%
#8800
0%
#8820
1-
b11 4
1%
#8840
0%
#8860
1+
1)
0-
b100 4
1%
#8880
0%
#8900
0+
0)
b1 4
b1001101001000000 7
b1001101001000000 ;
b1001101001000000 ?
b1011 6
b1011 :
b1011 @
1%
#8920
0%
#8940
b10 4
1%
#8960
0%
#8980
1-
b11 4
1%
#9000
0%
#9020
1+
1)
0-
b100 4
1%
#9040
0%
#9060
0+
0)
b1 "
b1 ,
b1 9
b1 8
b1 <
b1 =
b1 4
b10011010010000000 7
b10011010010000000 ;
b10011010010000000 ?
b1010 6
b1010 :
b1010 @
1%
#9080
0%
#9100
b10 4
1%
#9120
0%
#9140
1-
b11 4
1%
#9160
0%
#9180
1+
1)
0-
b100 4
1%
#9200
0%
#9220
0+
0)
b10 "
b10 ,
b10 9
b10 8
b10 <
b10 =
b1 4
b100110100100000000 7
b100110100100000000 ;
b100110100100000000 ?
b1001 6
b1001 :
b1001 @
1%
#9240
0%
#9260
b10 4
1%
#9280
0%
#9300
1-
b11 4
1%
#9320
0%
#9340
1+
1)
0-
b100 4
1%
#9360
0%
#9380
0+
0)
b100 "
b100 ,
b100 9
b100 8
b100 <
b100 =
b1 4
b1001101001000000000 7
b1001101001000000000 ;
b1001101001000000000 ?
b1000 6
b1000 :
b1000 @
1%
#9400
0%
#9420
b10 4
1%
#9440
0%
#9460
1-
b11 4
1%
#9480
0%
#9500
1+
1)
0-
b100 4
1%
#9520
0%
#9540
0+
0)
b1001 "
b1001 ,
b1001 9
b1100 8
b1100 <
b1100 =
b1 4
b10011010010000000000 7
b10011010010000000000 ;
b10011010010000000000 ?
b111 6
b111 :
b111 @
1%
#9560
0%
#9580
b10 4
1%
#9600
0%
#9620
1-
b11 4
1%
#9640
0%
#9660
b1100 "
b1100 ,
b1100 9
b1111 8
b1111 <
b1111 =
1+
1)
0-
b11001010010000000000 7
b11001010010000000000 ;
b11001010010000000000 ?
b100 4
1%
#9680
0%
#9700
0+
0)
b11001 "
b11001 ,
b11001 9
b11100 8
b11100 <
b11100 =
b1 4
b110010100100000000000 7
b110010100100000000000 ;
b110010100100000000000 ?
b110 6
b110 :
b110 @
1%
#9720
0%
#9740
b10 4
1%
#9760
0%
#9780
1-
b11 4
1%
#9800
0%
#9820
b11100 "
b11100 ,
b11100 9
b11111 8
b11111 <
b11111 =
1+
1)
0-
b111000100100000000000 7
b111000100100000000000 ;
b111000100100000000000 ?
b100 4
1%
#9840
0%
#9860
0+
0)
b111000 "
b111000 ,
b111000 9
b111011 8
b111011 <
b111011 =
b1 4
b1110001001000000000000 7
b1110001001000000000000 ;
b1110001001000000000000 ?
b101 6
b101 :
b101 @
1%
#9880
0%
#9900
b10 4
1%
#9920
0%
#9940
1-
b11 4
1%
#9960
0%
#9980
b111011 "
b111011 ,
b111011 9
b111110 8
b111110 <
b111110 =
1+
1)
0-
b1110111001000000000000 7
b1110111001000000000000 ;
b1110111001000000000000 ?
b100 4
1%
#10000
0%
#10020
0+
0)
b1110111 "
b1110111 ,
b1110111 9
b10101010 8
b10101010 <
b10101010 =
b1 4
b11101110010000000000000 7
b11101110010000000000000 ;
b11101110010000000000000 ?
b100 6
b100 :
b100 @
1%
#10040
0%
#10060
b10 4
1%
#10080
0%
#10100
1-
b11 4
1%
#10120
0%
#10140
b10101010 "
b10101010 ,
b10101010 9
b11011101 8
b11011101 <
b11011101 =
1+
1)
0-
b101010100010000000000000 7
b101010100010000000000000 ;
b101010100010000000000000 ?
b100 4
1%
#10160
0%
#10180
0+
0)
b101010100 "
b101010100 ,
b101010100 9
b110000100 8
b110000100 <
b110000100 =
b1 4
b1010101000100000000000000 7
b1010101000100000000000000 ;
b1010101000100000000000000 ?
b11 6
b11 :
b11 @
1%
#10200
0%
#10220
b10 4
1%
#10240
0%
#10260
1-
b11 4
1%
#10280
0%
#10300
b110000100 "
b110000100 ,
b110000100 9
b110110100 8
b110110100 <
b110110100 =
1+
1)
0-
b1100001000100000000000000 7
b1100001000100000000000000 ;
b1100001000100000000000000 ?
b100 4
1%
#10320
0%
#10340
0+
0)
b1100001000 "
b1100001000 ,
b1100001000 9
b1100001011 8
b1100001011 <
b1100001011 =
b1 4
b11000010001000000000000000 7
b11000010001000000000000000 ;
b11000010001000000000000000 ?
b10 6
b10 :
b10 @
1%
#10360
0%
#10380
b10 4
1%
#10400
0%
#10420
1-
b11 4
1%
#10440
0%
#10460
b1100001011 "
b1100001011 ,
b1100001011 9
b1100001110 8
b1100001110 <
b1100001110 =
1+
1)
0-
b11000010111000000000000000 7
b11000010111000000000000000 ;
b11000010111000000000000000 ?
b100 4
1%
#10480
0%
#10500
0+
0)
b11000010111 "
b11000010111 ,
b11000010111 9
b100100011010 8
b100100011010 <
b100100011010 =
b1 4
b110000101110000000000000000 7
b110000101110000000000000000 ;
b110000101110000000000000000 ?
b1 6
b1 :
b1 @
1%
#10520
0%
#10540
b10 4
1%
#10560
0%
#10580
1-
b11 4
1%
#10600
0%
#10620
b100100011010 "
b100100011010 ,
b100100011010 9
b110000011101 8
b110000011101 <
b110000011101 =
1+
1)
0-
b1001000110100000000000000000 7
b1001000110100000000000000000 ;
b1001000110100000000000000000 ?
b100 4
1%
#10640
0%
#10660
0+
0)
b1001000110100 "
b1001000110100 ,
b1001000110100 9
b1001000110100 8
b1001000110100 <
b1001000110100 =
b1 4
b10010001101000000000000000000 7
b10010001101000000000000000000 ;
b10010001101000000000000000000 ?
1(
b0 6
b0 :
b0 @
1%
#10680
0%
#10700
1!
b101 4
1%
#10720
0%
