DEFINITIVOS/PARIDAD/Control.v
module Control (
    clk,
    rst,
    INIT,
    Cero,
    LBS,
    Cargar,
    Corrimiento,
    Decremento,
    Incremento,
    DONE
);

input clk;
input rst;
input INIT;
input Cero;
input LBS;
output reg Cargar;
output reg Corrimiento;
output reg Decremento;
output reg Incremento;
output reg DONE;

parameter Inicio    = 3'b000; // Cargar=1
parameter Chequeo1  = 3'b001; // pregunta Cero
parameter Chequeo2  = 3'b010; // pregunta LBS(RegistroA)
parameter IncCarga  = 3'b011; // LBS=1 -> Incremento=1, Cargar=1
parameter ShiftDec  = 3'b100; // LBS=0 -> Decremento=1, Corrimiento=1
parameter Final     = 3'b101; // Cero=1 -> Done=1

reg [2:0] STATE;

always @(posedge clk or posedge rst) begin
    if (rst)
        STATE <= Inicio;
    else begin
        case (STATE)
            Inicio: begin
                if (INIT)
                    STATE <= Chequeo1;
                else
                    STATE <= Inicio;
            end
            Chequeo1: begin
                if (Cero)
                    STATE <= Final;
                else
                    STATE <= Chequeo2;
            end
            Chequeo2: begin
                if (LBS)
                    STATE <= IncCarga;
                else
                    STATE <= ShiftDec;
            end
            IncCarga: begin
                STATE <= ShiftDec;
            end
            ShiftDec: begin
                STATE <= Chequeo1;
            end
            Final: begin
                STATE <= Inicio;
            end
            default: STATE <= Inicio;
        endcase
    end
end

always @(*) begin
    case (STATE)
        Inicio: begin
            Cargar      = 1;
            Corrimiento = 0;
            Decremento  = 0;
            Incremento  = 0;
            DONE        = 0;
        end
        Chequeo1: begin
            Cargar      = 0;
            Corrimiento = 0;
            Decremento  = 0;
            Incremento  = 0;
            DONE        = 0;
        end
        Chequeo2: begin
            Cargar      = 0;
            Corrimiento = 0;
            Decremento  = 0;
            Incremento  = 0;
            DONE        = 0;
        end
        IncCarga: begin
            Cargar      = 0;
            Corrimiento = 0;
            Decremento  = 0;
            Incremento  = 1;
            DONE        = 0;
        end
        ShiftDec: begin
            Cargar      = 0;
            Corrimiento = 1;
            Decremento  = 1;
            Incremento  = 0;
            DONE        = 0;
        end
        Final: begin
            Cargar      = 0;
            Corrimiento = 0;
            Decremento  = 0;
            Incremento  = 0;
            DONE        = 1;
        end
        default: begin
            Cargar      = 0;
            Corrimiento = 0;
            Decremento  = 0;
            Incremento  = 0;
            DONE        = 0;
        end
    endcase
end

`ifdef BENCH
reg [8*20:1] estado_nombre;
always @(*) begin
    case (STATE)
        Inicio:   estado_nombre = "INICIO";
        Chequeo1: estado_nombre = "CHEQUEO1";
        Chequeo2: estado_nombre = "CHEQUEO2";
        IncCarga: estado_nombre = "INC_CARGA";
        ShiftDec: estado_nombre = "SHIFT_DEC";
        Final:    estado_nombre = "FINAL";
        default:  estado_nombre = "unknown";
    endcase
end
`endif

endmodule

DEFINITIVOS/PARIDAD/Control_TB.v
module Control_TB;
reg clk;
reg rst;
reg INIT;
reg Cero;
reg LBS;
wire Cargar;
wire Corrimiento;
wire Decremento;
wire Incremento;
wire DONE;

Control uut (
    .clk(clk), .rst(rst), .INIT(INIT), .Cero(Cero), .LBS(LBS),
    .Cargar(Cargar), .Corrimiento(Corrimiento), .Decremento(Decremento),
    .Incremento(Incremento), .DONE(DONE)
);

initial begin
    clk = 0;
    forever #20 clk = ~clk;
end

initial begin
    $dumpfile("Control_TB.vcd");
    $dumpvars(0, Control_TB);

    rst = 1;
    INIT = 0;
    Cero = 0;
    LBS = 0;
    @(posedge clk);
    rst = 0;

    // Caso 1: el número llega directo a cero (EntradaBits = 0)
    @(posedge clk);
    INIT = 1;
    @(posedge clk);
    INIT = 0;
    @(posedge clk);
    Cero = 1;
    @(posedge clk);
    Cero = 0;
    #40;

    // Caso 2: recorre un bit en 1 y luego uno en 0 antes de terminar
    @(posedge clk);
    rst = 1;
    @(posedge clk);
    rst = 0;
    INIT = 1;
    @(posedge clk);
    INIT = 0;
    @(posedge clk);
    LBS = 1;
    @(posedge clk);
    LBS = 0;
    @(posedge clk);
    @(posedge clk);
    LBS = 0;
    @(posedge clk);
    Cero = 1;
    @(posedge clk);
    Cero = 0;
    #40;

    $finish;
end

endmodule

DEFINITIVOS/PARIDAD/Control_TB.vcd
$date
	Mon Jul 13 12:26:44 2026
$end
$version
	Icarus Verilog
$end
$timescale
	1s
$end
$scope module Control_TB $end
$var wire 1 ! Incremento $end
$var wire 1 " Decremento $end
$var wire 1 # DONE $end
$var wire 1 $ Corrimiento $end
$var wire 1 % Cargar $end
$var reg 1 & Cero $end
$var reg 1 ' INIT $end
$var reg 1 ( LBS $end
$var reg 1 ) clk $end
$var reg 1 * rst $end
$scope module uut $end
$var wire 1 & Cero $end
$var wire 1 ' INIT $end
$var wire 1 ( LBS $end
$var wire 1 ) clk $end
$var wire 1 * rst $end
$var parameter 3 + Chequeo1 $end
$var parameter 3 , Chequeo2 $end
$var parameter 3 - Final $end
$var parameter 3 . IncCarga $end
$var parameter 3 / Inicio $end
$var parameter 3 0 ShiftDec $end
$var reg 1 % Cargar $end
$var reg 1 $ Corrimiento $end
$var reg 1 # DONE $end
$var reg 1 " Decremento $end
$var reg 1 ! Incremento $end
$var reg 3 1 STATE [2:0] $end
$var reg 160 2 estado_nombre [160:1] $end
$upscope $end
$upscope $end
$enddefinitions $end
$comment Show the parameter values. $end
$dumpall
b100 0
b0 /
b11 .
b101 -
b10 ,
b1 +
$end
#0
$dumpvars
b10010010100111001001001010000110100100101001111 2
b0 1
1*
0)
0(
0'
0&
1%
0$
0#
0"
0!
$end
#20
0*
1)
#40
0)
#60
0%
b100001101001000010001010101000101010101010001010100111100110001 2
b1 1
1'
1)
#80
0)
#100
b100001101001000010001010101000101010101010001010100111100110010 2
b10 1
0'
1)
#120
0)
#140
1"
1$
b10100110100100001001001010001100101010001011111010001000100010101000011 2
b100 1
1&
1)
#160
0)
#180
b100001101001000010001010101000101010101010001010100111100110001 2
0"
0$
b1 1
0&
1)
#200
0)
#220
1%
b10010010100111001001001010000110100100101001111 2
b0 1
1*
1)
#240
0)
#260
b100001101001000010001010101000101010101010001010100111100110001 2
0%
b1 1
1'
0*
1)
#280
0)
#300
b100001101001000010001010101000101010101010001010100111100110010 2
b10 1
0'
1)
#320
0)
#340
b10010010100111001000011010111110100001101000001010100100100011101000001 2
1!
b11 1
1(
1)
#360
0)
#380
0!
1"
1$
b10100110100100001001001010001100101010001011111010001000100010101000011 2
b100 1
0(
1)
#400
0)
#420
b100001101001000010001010101000101010101010001010100111100110001 2
0"
0$
b1 1
1)
#440
0)
#460
b100001101001000010001010101000101010101010001010100111100110010 2
b10 1
1)
#480
0)
#500
b10100110100100001001001010001100101010001011111010001000100010101000011 2
1"
1$
b100 1
1&
1)
#520
0)
#540
0"
0$
b100001101001000010001010101000101010101010001010100111100110001 2
b1 1
0&
1)
#560
0)
#580
b100001101001000010001010101000101010101010001010100111100110010 2
b10 1
1)
