DEFINITIVOS/PARIDAD/ContadorPosicion.v
module ContadorPosicion (clk, Cargar, Decremento, Cero);
input clk;
input Cargar;
input Decremento;
output Cero;

reg [3:0] ContadorPosicion;
assign Cero = (ContadorPosicion == 4'b0000);

always @(posedge clk) begin
    if (Cargar)
        ContadorPosicion <= 4'b1001; // 4'b9
    else if (Decremento)
        ContadorPosicion <= ContadorPosicion - 1;
end

endmodule

DEFINITIVOS/PARIDAD/ContadorPosicion_TB.v
module ContadorPosicion_TB;
reg clk;
reg Cargar;
reg Decremento;
wire Cero;

ContadorPosicion uut (.clk(clk), .Cargar(Cargar), .Decremento(Decremento), .Cero(Cero));

initial begin
    clk = 0;
    forever #20 clk = ~clk;
end

initial begin
    $dumpfile("ContadorPosicion_TB.vcd");
    $dumpvars(0, ContadorPosicion_TB);

    Cargar = 0;
    Decremento = 0;
    @(posedge clk);
    Cargar = 1;
    @(posedge clk);
    Cargar = 0;
    @(posedge clk);
    Decremento = 1;
    wait(Cero);
    Decremento = 0;
    #40;

    @(posedge clk);
    Cargar = 1;
    @(posedge clk);
    Cargar = 0;
    Decremento = 1;
    repeat(5) @(posedge clk);
    Decremento = 0;
    #40;

    $finish;
end

endmodule

DEFINITIVOS/PARIDAD/ContadorPosicion_TB.vcd
$date
	Mon Jul 13 12:29:51 2026
$end
$version
	Icarus Verilog
$end
$timescale
	1s
$end
$scope module ContadorPosicion_TB $end
$var wire 1 ! Cero $end
$var reg 1 " Cargar $end
$var reg 1 # Decremento $end
$var reg 1 $ clk $end
$scope module uut $end
$var wire 1 " Cargar $end
$var wire 1 # Decremento $end
$var wire 1 $ clk $end
$var wire 1 ! Cero $end
$var reg 4 % ContadorPosicion [3:0] $end
$upscope $end
$upscope $end
$enddefinitions $end
$comment Show the parameter values. $end
$dumpall
$end
#0
$dumpvars
bx %
0$
0#
0"
x!
$end
#20
0!
b1001 %
1"
1$
#40
0$
#60
0"
1$
#80
0$
#100
b1000 %
1#
1$
#120
0$
#140
b111 %
1$
#160
0$
#180
b110 %
1$
#200
0$
#220
b101 %
1$
#240
0$
#260
b100 %
1$
#280
0$
#300
b11 %
1$
#320
0$
#340
b10 %
1$
#360
0$
#380
b1 %
1$
#400
0$
#420
0#
1!
b0 %
1$
#440
0$
#460
0!
b1001 %
1"
1$
#480
0$
#500
1#
0"
1$
#520
0$
#540
b1000 %
1$
#560
0$
#580
b111 %
1$
#600
0$
#620
b110 %
1$
#640
0$
#660
b101 %
1$
#680
0$
#700
0#
1$
