DEFINITIVOS/PARIDAD/Control.v
module Control (
    clk,
    rst,
    INIT,
    Cero,
    LBS,
    Cargar,
    Corrimiento,
    Decremento,
    Incremento,
    DONE
);

input clk;
input rst;
input INIT;
input Cero;
input LBS;
output reg Cargar;
output reg Corrimiento;
output reg Decremento;
output reg Incremento;
output reg DONE;

parameter Inicio    = 3'b000; // Cargar=1
parameter Chequeo1  = 3'b001; // pregunta Cero
parameter Chequeo2  = 3'b010; // pregunta LBS(RegistroA)
parameter IncCarga  = 3'b011; // LBS=1 -> Incremento=1, Cargar=1
parameter ShiftDec  = 3'b100; // LBS=0 -> Decremento=1, Corrimiento=1
parameter Final     = 3'b101; // Cero=1 -> Done=1

reg [2:0] STATE;

always @(posedge clk or posedge rst) begin
    if (rst)
        STATE <= Inicio;
    else begin
        case (STATE)
            Inicio: begin
                if (INIT)
                    STATE <= Chequeo1;
                else
                    STATE <= Inicio;
            end
            Chequeo1: begin
                if (Cero)
                    STATE <= Final;
                else
                    STATE <= Chequeo2;
            end
            Chequeo2: begin
                if (LBS)
                    STATE <= IncCarga;
                else
                    STATE <= ShiftDec;
            end
            IncCarga: begin
                STATE <= ShiftDec;
            end
            ShiftDec: begin
                STATE <= Chequeo1;
            end
            Final: begin
                STATE <= Inicio;
            end
            default: STATE <= Inicio;
        endcase
    end
end

always @(*) begin
    case (STATE)
        Inicio: begin
            Cargar      = 1;
            Corrimiento = 0;
            Decremento  = 0;
            Incremento  = 0;
            DONE        = 0;
        end
        Chequeo1: begin
            Cargar      = 0;
            Corrimiento = 0;
            Decremento  = 0;
            Incremento  = 0;
            DONE        = 0;
        end
        Chequeo2: begin
            Cargar      = 0;
            Corrimiento = 0;
            Decremento  = 0;
            Incremento  = 0;
            DONE        = 0;
        end
        IncCarga: begin
            Cargar      = 0;
            Corrimiento = 0;
            Decremento  = 0;
            Incremento  = 1;
            DONE        = 0;
        end
        ShiftDec: begin
            Cargar      = 0;
            Corrimiento = 1;
            Decremento  = 1;
            Incremento  = 0;
            DONE        = 0;
        end
        Final: begin
            Cargar      = 0;
            Corrimiento = 0;
            Decremento  = 0;
            Incremento  = 0;
            DONE        = 1;
        end
        default: begin
            Cargar      = 0;
            Corrimiento = 0;
            Decremento  = 0;
            Incremento  = 0;
            DONE        = 0;
        end
    endcase
end

`ifdef BENCH
reg [8*20:1] estado_nombre;
always @(*) begin
    case (STATE)
        Inicio:   estado_nombre = "INICIO";
        Chequeo1: estado_nombre = "CHEQUEO1";
        Chequeo2: estado_nombre = "CHEQUEO2";
        IncCarga: estado_nombre = "INC_CARGA";
        ShiftDec: estado_nombre = "SHIFT_DEC";
        Final:    estado_nombre = "FINAL";
        default:  estado_nombre = "unknown";
    endcase
end
`endif

endmodule

DEFINITIVOS/PARIDAD/ContadorPosicion.v
module ContadorPosicion (clk, Cargar, Decremento, Cero);
input clk;
input Cargar;
input Decremento;
output Cero;

reg [3:0] ContadorPosicion;
assign Cero = (ContadorPosicion == 4'b0000);

always @(posedge clk) begin
    if (Cargar)
        ContadorPosicion <= 4'b1001; // 4'b9
    else if (Decremento)
        ContadorPosicion <= ContadorPosicion - 1;
end

endmodule

DEFINITIVOS/PARIDAD/ContadorUno.v
module ContadorUno (clk, Cargar, Incremento, Cantidad, Paridad);
input clk;
input Cargar;
input Incremento;
output [3:0] Cantidad;
output Paridad;
 
reg [3:0] ContadorUno;
assign Cantidad = ContadorUno;
assign Paridad  = ContadorUno[0];
 
always @(posedge clk) begin
    if (Cargar)
        ContadorUno <= 4'b0000;
    else if (Incremento)
        ContadorUno <= ContadorUno + 1;
end
 
endmodule

DEFINITIVOS/PARIDAD/RegistroA.v
module RegistroA (clk, Cargar, Corrimiento, EntradaBits, LBS);
input clk;
input Cargar;
input Corrimiento;
input [8:0] EntradaBits;
output LBS;

reg [8:0] RegistroA;
assign LBS = RegistroA[0];

always @(posedge clk) begin
    if (Cargar)
        RegistroA <= EntradaBits;
    else if (Corrimiento)
        RegistroA <= RegistroA >> 1;
end

endmodule

DEFINITIVOS/PARIDAD/CaminoDeDatos.v
module CaminoDeDatos (
    clk,
    EntradaBits,
    Cargar,
    Corrimiento,
    Incremento,
    Decremento,
    LBS,
    Cero,
    Cantidad,
    Paridad
);
input clk;
input [8:0] EntradaBits;
input Cargar;
input Corrimiento;
input Incremento;
input Decremento;
output LBS;
output Cero;
output [3:0] Cantidad;
output Paridad;
 
RegistroA regA0 (
    .clk(clk),
    .Cargar(Cargar),
    .Corrimiento(Corrimiento),
    .EntradaBits(EntradaBits),
    .LBS(LBS)
);
 
ContadorUno contadorUno0 (
    .clk(clk),
    .Cargar(Cargar),
    .Incremento(Incremento),
    .Cantidad(Cantidad),
    .Paridad(Paridad)
);
 
ContadorPosicion contadorPosicion0 (
    .clk(clk),
    .Cargar(Cargar),
    .Decremento(Decremento),
    .Cero(Cero)
);
 
endmodule

DEFINITIVOS/PARIDAD/Paridad.v
module Paridad (
    clk,
    rst,
    INIT,
    EntradaBits,
    Cantidad,
    Paridad,
    DONE
);

input clk;
input rst;
input INIT;
input [8:0] EntradaBits;
output [3:0] Cantidad;
output Paridad;
output DONE;

wire Cargar;
wire Corrimiento;
wire Decremento;
wire Incremento;
wire Cero;
wire LBS;

CaminoDeDatos caminoDeDatos0 (
    .clk(clk),
    .EntradaBits(EntradaBits),
    .Cargar(Cargar),
    .Corrimiento(Corrimiento),
    .Incremento(Incremento),
    .Decremento(Decremento),
    .LBS(LBS),
    .Cero(Cero),
    .Cantidad(Cantidad),
    .Paridad(Paridad)
);

Control control0 (
    .clk(clk),
    .rst(rst),
    .INIT(INIT),
    .Cero(Cero),
    .LBS(LBS),
    .Cargar(Cargar),
    .Corrimiento(Corrimiento),
    .Decremento(Decremento),
    .Incremento(Incremento),
    .DONE(DONE)
);

endmodule

DEFINITIVOS/PARIDAD/Paridad_TB.v
module Paridad_TB;
reg clk;
reg rst;
reg INIT;
reg [8:0] EntradaBits;
wire [3:0] Cantidad;
wire Paridad;
wire DONE;

Paridad uut (
    .clk(clk), .rst(rst), .INIT(INIT), .EntradaBits(EntradaBits),
    .Cantidad(Cantidad), .Paridad(Paridad), .DONE(DONE)
);

initial begin
    clk = 0;
    forever #20 clk = ~clk;
end

task correr_caso(input [8:0] valor);
    begin
        EntradaBits = valor;
        @(posedge clk);
        rst = 1;
        @(posedge clk);
        rst = 0;
        INIT = 1;
        @(posedge clk);
        INIT = 0;
        wait(DONE);
        #40;
    end
endtask

initial begin
    $dumpfile("Paridad_TB.vcd");
    $dumpvars(0, Paridad_TB);

    rst = 1;
    INIT = 0;
    EntradaBits = 9'b0;
    @(posedge clk);
    rst = 0;
    #40;

    correr_caso(9'b000000000); // 0 unos  -> Cantidad=0, Paridad=0
    correr_caso(9'b000001111); // 4 unos  -> Cantidad=4, Paridad=0
    correr_caso(9'b111111111); // 9 unos  -> Cantidad=9, Paridad=1
    correr_caso(9'b101010101); // 5 unos  -> Cantidad=5, Paridad=1

    $finish;
end

endmodule

DEFINITIVOS/PARIDAD/Paridad_TB.vcd
$date
	Fri Jul 10 23:33:17 2026
$end
$version
	Icarus Verilog
$end
$timescale
	1s
$end
$scope module Paridad_TB $end
$var wire 1 ! Paridad $end
$var wire 1 " DONE $end
$var wire 4 # Cantidad [3:0] $end
$var reg 9 $ EntradaBits [8:0] $end
$var reg 1 % INIT $end
$var reg 1 & clk $end
$var reg 1 ' rst $end
$scope module uut $end
$var wire 9 ( EntradaBits [8:0] $end
$var wire 1 % INIT $end
$var wire 1 & clk $end
$var wire 1 ' rst $end
$var wire 1 ! Paridad $end
$var wire 1 ) LBS $end
$var wire 1 * Incremento $end
$var wire 1 + Decremento $end
$var wire 1 " DONE $end
$var wire 1 , Corrimiento $end
$var wire 1 - Cero $end
$var wire 1 . Cargar $end
$var wire 4 / Cantidad [3:0] $end
$scope module caminoDeDatos0 $end
$var wire 9 0 EntradaBits [8:0] $end
$var wire 1 & clk $end
$var wire 1 ! Paridad $end
$var wire 1 ) LBS $end
$var wire 1 * Incremento $end
$var wire 1 + Decremento $end
$var wire 1 , Corrimiento $end
$var wire 1 - Cero $end
$var wire 1 . Cargar $end
$var wire 4 1 Cantidad [3:0] $end
$scope module contadorPosicion0 $end
$var wire 1 & clk $end
$var wire 1 + Decremento $end
$var wire 1 - Cero $end
$var wire 1 . Cargar $end
$var reg 4 2 ContadorPosicion [3:0] $end
$upscope $end
$scope module contadorUno0 $end
$var wire 4 3 Cantidad [3:0] $end
$var wire 1 & clk $end
$var wire 1 ! Paridad $end
$var wire 1 * Incremento $end
$var wire 1 . Cargar $end
$var reg 4 4 ContadorUno [3:0] $end
$upscope $end
$scope module regA0 $end
$var wire 9 5 EntradaBits [8:0] $end
$var wire 1 & clk $end
$var wire 1 ) LBS $end
$var wire 1 , Corrimiento $end
$var wire 1 . Cargar $end
$var reg 9 6 RegistroA [8:0] $end
$upscope $end
$upscope $end
$scope module control0 $end
$var wire 1 - Cero $end
$var wire 1 % INIT $end
$var wire 1 ) LBS $end
$var wire 1 & clk $end
$var wire 1 ' rst $end
$var parameter 3 7 Chequeo1 $end
$var parameter 3 8 Chequeo2 $end
$var parameter 3 9 Final $end
$var parameter 3 : IncCarga $end
$var parameter 3 ; Inicio $end
$var parameter 3 < ShiftDec $end
$var reg 1 . Cargar $end
$var reg 1 , Corrimiento $end
$var reg 1 " DONE $end
$var reg 1 + Decremento $end
$var reg 1 * Incremento $end
$var reg 3 = STATE [2:0] $end
$var reg 160 > estado_nombre [160:1] $end
$upscope $end
$upscope $end
$scope task correr_caso $end
$var reg 9 ? valor [8:0] $end
$upscope $end
$upscope $end
$enddefinitions $end
$comment Show the parameter values. $end
$dumpall
b100 <
b0 ;
b11 :
b101 9
b10 8
b1 7
$end
#0
$dumpvars
bx ?
b10010010100111001001001010000110100100101001111 >
b0 =
bx 6
b0 5
bx 4
bx 3
bx 2
bx 1
b0 0
bx /
1.
x-
0,
0+
0*
x)
b0 (
1'
0&
0%
b0 $
bx #
0"
x!
$end
#20
0)
0!
b0 6
b0 #
b0 /
b0 1
b0 3
b0 4
0-
b1001 2
0'
1&
#40
0&
#60
1'
1&
b0 ?
#80
0&
#100
0.
b100001101001000010001010101000101010101010001010100111100110001 >
b1 =
1%
0'
1&
#120
0&
#140
b100001101001000010001010101000101010101010001010100111100110010 >
b10 =
0%
1&
#160
0&
#180
1+
1,
b10100110100100001001001010001100101010001011111010001000100010101000011 >
b100 =
1&
#200
0&
#220
b100001101001000010001010101000101010101010001010100111100110001 >
0+
0,
b1 =
b1000 2
1&
#240
0&
#260
b100001101001000010001010101000101010101010001010100111100110010 >
b10 =
1&
#280
0&
#300
b10100110100100001001001010001100101010001011111010001000100010101000011 >
1+
1,
b100 =
1&
#320
0&
#340
0+
0,
b100001101001000010001010101000101010101010001010100111100110001 >
b1 =
b111 2
1&
#360
0&
#380
b100001101001000010001010101000101010101010001010100111100110010 >
b10 =
1&
#400
0&
#420
1+
1,
b10100110100100001001001010001100101010001011111010001000100010101000011 >
b100 =
1&
#440
0&
#460
b100001101001000010001010101000101010101010001010100111100110001 >
0+
0,
b1 =
b110 2
1&
#480
0&
#500
b100001101001000010001010101000101010101010001010100111100110010 >
b10 =
1&
#520
0&
#540
b10100110100100001001001010001100101010001011111010001000100010101000011 >
1+
1,
b100 =
1&
#560
0&
#580
0+
0,
b100001101001000010001010101000101010101010001010100111100110001 >
b1 =
b101 2
1&
#600
0&
#620
b100001101001000010001010101000101010101010001010100111100110010 >
b10 =
1&
#640
0&
#660
1+
1,
b10100110100100001001001010001100101010001011111010001000100010101000011 >
b100 =
1&
#680
0&
#700
b100001101001000010001010101000101010101010001010100111100110001 >
0+
0,
b1 =
b100 2
1&
#720
0&
#740
b100001101001000010001010101000101010101010001010100111100110010 >
b10 =
1&
#760
0&
#780
b10100110100100001001001010001100101010001011111010001000100010101000011 >
1+
1,
b100 =
1&
#800
0&
#820
0+
0,
b100001101001000010001010101000101010101010001010100111100110001 >
b1 =
b11 2
1&
#840
0&
#860
b100001101001000010001010101000101010101010001010100111100110010 >
b10 =
1&
#880
0&
#900
1+
1,
b10100110100100001001001010001100101010001011111010001000100010101000011 >
b100 =
1&
#920
0&
#940
b100001101001000010001010101000101010101010001010100111100110001 >
0+
0,
b1 =
b10 2
1&
#960
0&
#980
b100001101001000010001010101000101010101010001010100111100110010 >
b10 =
1&
#1000
0&
#1020
b10100110100100001001001010001100101010001011111010001000100010101000011 >
1+
1,
b100 =
1&
#1040
0&
#1060
0+
0,
b100001101001000010001010101000101010101010001010100111100110001 >
b1 =
b1 2
1&
#1080
0&
#1100
b100001101001000010001010101000101010101010001010100111100110010 >
b10 =
1&
#1120
0&
#1140
1+
1,
b10100110100100001001001010001100101010001011111010001000100010101000011 >
b100 =
1&
#1160
0&
#1180
b100001101001000010001010101000101010101010001010100111100110001 >
0+
0,
b1 =
1-
b0 2
1&
#1200
0&
#1220
1"
b100011001001001010011100100000101001100 >
b101 =
1&
#1240
0&
#1260
b10010010100111001001001010000110100100101001111 >
0"
1.
b0 =
1'
1&
b1111 $
b1111 (
b1111 0
b1111 5
b1111 ?
#1280
0&
#1300
0.
b100001101001000010001010101000101010101010001010100111100110001 >
1)
b1 =
b1111 6
0-
b1001 2
1%
0'
1&
#1320
0&
#1340
b100001101001000010001010101000101010101010001010100111100110010 >
b10 =
0%
1&
#1360
0&
#1380
1*
b10010010100111001000011010111110100001101000001010100100100011101000001 >
b11 =
1&
#1400
0&
#1420
b10100110100100001001001010001100101010001011111010001000100010101000011 >
0*
1+
1,
1!
b100 =
b1 #
b1 /
b1 1
b1 3
b1 4
1&
#1440
0&
#1460
0+
0,
b100001101001000010001010101000101010101010001010100111100110001 >
b1 =
b111 6
b1000 2
1&
#1480
0&
#1500
b100001101001000010001010101000101010101010001010100111100110010 >
b10 =
1&
#1520
0&
#1540
1*
b10010010100111001000011010111110100001101000001010100100100011101000001 >
b11 =
1&
#1560
0&
#1580
b10100110100100001001001010001100101010001011111010001000100010101000011 >
0*
1+
1,
0!
b100 =
b10 #
b10 /
b10 1
b10 3
b10 4
1&
#1600
0&
#1620
0+
0,
b100001101001000010001010101000101010101010001010100111100110001 >
b1 =
b11 6
b111 2
1&
#1640
0&
#1660
b100001101001000010001010101000101010101010001010100111100110010 >
b10 =
1&
#1680
0&
#1700
1*
b10010010100111001000011010111110100001101000001010100100100011101000001 >
b11 =
1&
#1720
0&
#1740
b10100110100100001001001010001100101010001011111010001000100010101000011 >
0*
1+
1,
1!
b100 =
b11 #
b11 /
b11 1
b11 3
b11 4
1&
#1760
0&
#1780
0+
0,
b100001101001000010001010101000101010101010001010100111100110001 >
b1 =
b1 6
b110 2
1&
#1800
0&
#1820
b100001101001000010001010101000101010101010001010100111100110010 >
b10 =
1&
#1840
0&
#1860
1*
b10010010100111001000011010111110100001101000001010100100100011101000001 >
b11 =
1&
#1880
0&
#1900
b10100110100100001001001010001100101010001011111010001000100010101000011 >
0*
1+
1,
0!
b100 =
b100 #
b100 /
b100 1
b100 3
b100 4
1&
#1920
0&
#1940
0+
0,
b100001101001000010001010101000101010101010001010100111100110001 >
0)
b1 =
b0 6
b101 2
1&
#1960
0&
#1980
b100001101001000010001010101000101010101010001010100111100110010 >
b10 =
1&
#2000
0&
#2020
1+
1,
b10100110100100001001001010001100101010001011111010001000100010101000011 >
b100 =
1&
#2040
0&
#2060
b100001101001000010001010101000101010101010001010100111100110001 >
0+
0,
b1 =
b100 2
1&
#2080
0&
#2100
b100001101001000010001010101000101010101010001010100111100110010 >
b10 =
1&
#2120
0&
#2140
b10100110100100001001001010001100101010001011111010001000100010101000011 >
1+
1,
b100 =
1&
#2160
0&
#2180
0+
0,
b100001101001000010001010101000101010101010001010100111100110001 >
b1 =
b11 2
1&
#2200
0&
#2220
b100001101001000010001010101000101010101010001010100111100110010 >
b10 =
1&
#2240
0&
#2260
1+
1,
b10100110100100001001001010001100101010001011111010001000100010101000011 >
b100 =
1&
#2280
0&
#2300
b100001101001000010001010101000101010101010001010100111100110001 >
0+
0,
b1 =
b10 2
1&
#2320
0&
#2340
b100001101001000010001010101000101010101010001010100111100110010 >
b10 =
1&
#2360
0&
#2380
b10100110100100001001001010001100101010001011111010001000100010101000011 >
1+
1,
b100 =
1&
#2400
0&
#2420
0+
0,
b100001101001000010001010101000101010101010001010100111100110001 >
b1 =
b1 2
1&
#2440
0&
#2460
b100001101001000010001010101000101010101010001010100111100110010 >
b10 =
1&
#2480
0&
#2500
1+
1,
b10100110100100001001001010001100101010001011111010001000100010101000011 >
b100 =
1&
#2520
0&
#2540
b100001101001000010001010101000101010101010001010100111100110001 >
0+
0,
b1 =
1-
b0 2
1&
#2560
0&
#2580
1"
b100011001001001010011100100000101001100 >
b101 =
1&
#2600
0&
#2620
b10010010100111001001001010000110100100101001111 >
0"
1.
b0 =
1'
1&
b111111111 $
b111111111 (
b111111111 0
b111111111 5
b111111111 ?
#2640
0&
#2660
0.
b100001101001000010001010101000101010101010001010100111100110001 >
1)
b1 =
b111111111 6
b0 #
b0 /
b0 1
b0 3
b0 4
0-
b1001 2
1%
0'
1&
#2680
0&
#2700
b100001101001000010001010101000101010101010001010100111100110010 >
b10 =
0%
1&
#2720
0&
#2740
1*
b10010010100111001000011010111110100001101000001010100100100011101000001 >
b11 =
1&
#2760
0&
#2780
b10100110100100001001001010001100101010001011111010001000100010101000011 >
0*
1+
1,
1!
b100 =
b1 #
b1 /
b1 1
b1 3
b1 4
1&
#2800
0&
#2820
0+
0,
b100001101001000010001010101000101010101010001010100111100110001 >
b1 =
b11111111 6
b1000 2
1&
#2840
0&
#2860
b100001101001000010001010101000101010101010001010100111100110010 >
b10 =
1&
#2880
0&
#2900
1*
b10010010100111001000011010111110100001101000001010100100100011101000001 >
b11 =
1&
#2920
0&
#2940
b10100110100100001001001010001100101010001011111010001000100010101000011 >
0*
1+
1,
0!
b100 =
b10 #
b10 /
b10 1
b10 3
b10 4
1&
#2960
0&
#2980
0+
0,
b100001101001000010001010101000101010101010001010100111100110001 >
b1 =
b1111111 6
b111 2
1&
#3000
0&
#3020
b100001101001000010001010101000101010101010001010100111100110010 >
b10 =
1&
#3040
0&
#3060
1*
b10010010100111001000011010111110100001101000001010100100100011101000001 >
b11 =
1&
#3080
0&
#3100
b10100110100100001001001010001100101010001011111010001000100010101000011 >
0*
1+
1,
1!
b100 =
b11 #
b11 /
b11 1
b11 3
b11 4
1&
#3120
0&
#3140
0+
0,
b100001101001000010001010101000101010101010001010100111100110001 >
b1 =
b111111 6
b110 2
1&
#3160
0&
#3180
b100001101001000010001010101000101010101010001010100111100110010 >
b10 =
1&
#3200
0&
#3220
1*
b10010010100111001000011010111110100001101000001010100100100011101000001 >
b11 =
1&
#3240
0&
#3260
b10100110100100001001001010001100101010001011111010001000100010101000011 >
0*
1+
1,
0!
b100 =
b100 #
b100 /
b100 1
b100 3
b100 4
1&
#3280
0&
#3300
0+
0,
b100001101001000010001010101000101010101010001010100111100110001 >
b1 =
b11111 6
b101 2
1&
#3320
0&
#3340
b100001101001000010001010101000101010101010001010100111100110010 >
b10 =
1&
#3360
0&
#3380
1*
b10010010100111001000011010111110100001101000001010100100100011101000001 >
b11 =
1&
#3400
0&
#3420
b10100110100100001001001010001100101010001011111010001000100010101000011 >
0*
1+
1,
1!
b100 =
b101 #
b101 /
b101 1
b101 3
b101 4
1&
#3440
0&
#3460
0+
0,
b100001101001000010001010101000101010101010001010100111100110001 >
b1 =
b1111 6
b100 2
1&
#3480
0&
#3500
b100001101001000010001010101000101010101010001010100111100110010 >
b10 =
1&
#3520
0&
#3540
1*
b10010010100111001000011010111110100001101000001010100100100011101000001 >
b11 =
1&
#3560
0&
#3580
b10100110100100001001001010001100101010001011111010001000100010101000011 >
0*
1+
1,
0!
b100 =
b110 #
b110 /
b110 1
b110 3
b110 4
1&
#3600
0&
#3620
0+
0,
b100001101001000010001010101000101010101010001010100111100110001 >
b1 =
b111 6
b11 2
1&
#3640
0&
#3660
b100001101001000010001010101000101010101010001010100111100110010 >
b10 =
1&
#3680
0&
#3700
1*
b10010010100111001000011010111110100001101000001010100100100011101000001 >
b11 =
1&
#3720
0&
#3740
b10100110100100001001001010001100101010001011111010001000100010101000011 >
0*
1+
1,
1!
b100 =
b111 #
b111 /
b111 1
b111 3
b111 4
1&
#3760
0&
#3780
0+
0,
b100001101001000010001010101000101010101010001010100111100110001 >
b1 =
b11 6
b10 2
1&
#3800
0&
#3820
b100001101001000010001010101000101010101010001010100111100110010 >
b10 =
1&
#3840
0&
#3860
1*
b10010010100111001000011010111110100001101000001010100100100011101000001 >
b11 =
1&
#3880
0&
#3900
b10100110100100001001001010001100101010001011111010001000100010101000011 >
0*
1+
1,
0!
b100 =
b1000 #
b1000 /
b1000 1
b1000 3
b1000 4
1&
#3920
0&
#3940
0+
0,
b100001101001000010001010101000101010101010001010100111100110001 >
b1 =
b1 6
b1 2
1&
#3960
0&
#3980
b100001101001000010001010101000101010101010001010100111100110010 >
b10 =
1&
#4000
0&
#4020
1*
b10010010100111001000011010111110100001101000001010100100100011101000001 >
b11 =
1&
#4040
0&
#4060
b10100110100100001001001010001100101010001011111010001000100010101000011 >
0*
1+
1,
1!
b100 =
b1001 #
b1001 /
b1001 1
b1001 3
b1001 4
1&
#4080
0&
#4100
0+
0,
b100001101001000010001010101000101010101010001010100111100110001 >
0)
b1 =
b0 6
1-
b0 2
1&
#4120
0&
#4140
b100011001001001010011100100000101001100 >
1"
b101 =
1&
#4160
0&
#4180
0"
1.
b10010010100111001001001010000110100100101001111 >
b0 =
1'
1&
b101010101 $
b101010101 (
b101010101 0
b101010101 5
b101010101 ?
#4200
0&
#4220
b100001101001000010001010101000101010101010001010100111100110001 >
0.
0!
1)
b1 =
0-
b1001 2
b0 #
b0 /
b0 1
b0 3
b0 4
b101010101 6
1%
0'
1&
#4240
0&
#4260
b100001101001000010001010101000101010101010001010100111100110010 >
b10 =
0%
1&
#4280
0&
#4300
b10010010100111001000011010111110100001101000001010100100100011101000001 >
1*
b11 =
1&
#4320
0&
#4340
0*
1+
1,
b10100110100100001001001010001100101010001011111010001000100010101000011 >
1!
b100 =
b1 #
b1 /
b1 1
b1 3
b1 4
1&
#4360
0&
#4380
b100001101001000010001010101000101010101010001010100111100110001 >
0+
0,
0)
b1 =
b1000 2
b10101010 6
1&
#4400
0&
#4420
b100001101001000010001010101000101010101010001010100111100110010 >
b10 =
1&
#4440
0&
#4460
b10100110100100001001001010001100101010001011111010001000100010101000011 >
1+
1,
b100 =
1&
#4480
0&
#4500
0+
0,
b100001101001000010001010101000101010101010001010100111100110001 >
1)
b1 =
b1010101 6
b111 2
1&
#4520
0&
#4540
b100001101001000010001010101000101010101010001010100111100110010 >
b10 =
1&
#4560
0&
#4580
1*
b10010010100111001000011010111110100001101000001010100100100011101000001 >
b11 =
1&
#4600
0&
#4620
b10100110100100001001001010001100101010001011111010001000100010101000011 >
0*
1+
1,
0!
b100 =
b10 #
b10 /
b10 1
b10 3
b10 4
1&
#4640
0&
#4660
0+
0,
b100001101001000010001010101000101010101010001010100111100110001 >
0)
b1 =
b101010 6
b110 2
1&
#4680
0&
#4700
b100001101001000010001010101000101010101010001010100111100110010 >
b10 =
1&
#4720
0&
#4740
1+
1,
b10100110100100001001001010001100101010001011111010001000100010101000011 >
b100 =
1&
#4760
0&
#4780
b100001101001000010001010101000101010101010001010100111100110001 >
0+
0,
1)
b1 =
b101 2
b10101 6
1&
#4800
0&
#4820
b100001101001000010001010101000101010101010001010100111100110010 >
b10 =
1&
#4840
0&
#4860
b10010010100111001000011010111110100001101000001010100100100011101000001 >
1*
b11 =
1&
#4880
0&
#4900
0*
1+
1,
b10100110100100001001001010001100101010001011111010001000100010101000011 >
1!
b100 =
b11 #
b11 /
b11 1
b11 3
b11 4
1&
#4920
0&
#4940
b100001101001000010001010101000101010101010001010100111100110001 >
0+
0,
0)
b1 =
b100 2
b1010 6
1&
#4960
0&
#4980
b100001101001000010001010101000101010101010001010100111100110010 >
b10 =
1&
#5000
0&
#5020
b10100110100100001001001010001100101010001011111010001000100010101000011 >
1+
1,
b100 =
1&
#5040
0&
#5060
0+
0,
b100001101001000010001010101000101010101010001010100111100110001 >
1)
b1 =
b101 6
b11 2
1&
#5080
0&
#5100
b100001101001000010001010101000101010101010001010100111100110010 >
b10 =
1&
#5120
0&
#5140
1*
b10010010100111001000011010111110100001101000001010100100100011101000001 >
b11 =
1&
#5160
0&
#5180
b10100110100100001001001010001100101010001011111010001000100010101000011 >
0*
1+
1,
0!
b100 =
b100 #
b100 /
b100 1
b100 3
b100 4
1&
#5200
0&
#5220
0+
0,
b100001101001000010001010101000101010101010001010100111100110001 >
0)
b1 =
b10 6
b10 2
1&
#5240
0&
#5260
b100001101001000010001010101000101010101010001010100111100110010 >
b10 =
1&
#5280
0&
#5300
1+
1,
b10100110100100001001001010001100101010001011111010001000100010101000011 >
b100 =
1&
#5320
0&
#5340
b100001101001000010001010101000101010101010001010100111100110001 >
0+
0,
1)
b1 =
b1 2
b1 6
1&
#5360
0&
#5380
b100001101001000010001010101000101010101010001010100111100110010 >
b10 =
1&
#5400
0&
#5420
b10010010100111001000011010111110100001101000001010100100100011101000001 >
1*
b11 =
1&
#5440
0&
#5460
0*
1+
1,
b10100110100100001001001010001100101010001011111010001000100010101000011 >
1!
b100 =
b101 #
b101 /
b101 1
b101 3
b101 4
1&
#5480
0&
#5500
b100001101001000010001010101000101010101010001010100111100110001 >
0+
0,
0)
b1 =
1-
b0 2
b0 6
1&
#5520
0&
#5540
1"
b100011001001001010011100100000101001100 >
b101 =
1&
#5560
0&
#5580
b10010010100111001001001010000110100100101001111 >
0"
1.
b0 =
1&
