DEFINITIVOS/PARIDAD/RegistroA.v
module RegistroA (clk, Cargar, Corrimiento, EntradaBits, LBS);
input clk;
input Cargar;
input Corrimiento;
input [8:0] EntradaBits;
output LBS;

reg [8:0] RegistroA;
assign LBS = RegistroA[0];

always @(posedge clk) begin
    if (Cargar)
        RegistroA <= EntradaBits;
    else if (Corrimiento)
        RegistroA <= RegistroA >> 1;
end

endmodule

DEFINITIVOS/PARIDAD/RegistroA_TB.v
module RegistroA_TB;
reg clk;
reg Cargar;
reg Corrimiento;
reg [8:0] EntradaBits;
wire LBS;

RegistroA uut (.clk(clk), .Cargar(Cargar), .Corrimiento(Corrimiento), .EntradaBits(EntradaBits), .LBS(LBS));

initial begin
    clk = 0;
    forever #20 clk = ~clk;
end

initial begin
    $dumpfile("RegistroA_TB.vcd");
    $dumpvars(0, RegistroA_TB);

    Cargar = 0;
    Corrimiento = 0;
    EntradaBits = 9'b000011111;
    @(posedge clk);
    Cargar = 1;
    @(posedge clk);
    Cargar = 0;
    Corrimiento = 1;
    repeat(9) @(posedge clk);
    Corrimiento = 0;
    #40;

    EntradaBits = 9'b111111111;
    @(posedge clk);
    Cargar = 1;
    @(posedge clk);
    Cargar = 0;
    Corrimiento = 1;
    repeat(9) @(posedge clk);
    Corrimiento = 0;
    #40;

    EntradaBits = 9'b010101010;
    @(posedge clk);
    Cargar = 1;
    @(posedge clk);
    Cargar = 0;
    Corrimiento = 1;
    repeat(9) @(posedge clk);
    Corrimiento = 0;
    #40;

    $finish;
end

endmodule

DEFINITIVOS/PARIDAD/RegistroA_TB.vcd
$date
	Mon Jul 13 12:32:01 2026
$end
$version
	Icarus Verilog
$end
$timescale
	1s
$end
$scope module RegistroA_TB $end
$var wire 1 ! LBS $end
$var reg 1 " Cargar $end
$var reg 1 # Corrimiento $end
$var reg 9 $ EntradaBits [8:0] $end
$var reg 1 % clk $end
$scope module uut $end
$var wire 1 " Cargar $end
$var wire 1 # Corrimiento $end
$var wire 9 & EntradaBits [8:0] $end
$var wire 1 % clk $end
$var wire 1 ! LBS $end
$var reg 9 ' RegistroA [8:0] $end
$upscope $end
$upscope $end
$enddefinitions $end
$comment Show the parameter values. $end
$dumpall
$end
#0
$dumpvars
bx '
b11111 &
0%
b11111 $
0#
0"
x!
$end
#20
1!
b11111 '
1"
1%
#40
0%
#60
1#
0"
1%
#80
0%
#100
b1111 '
1%
#120
0%
#140
b111 '
1%
#160
0%
#180
b11 '
1%
#200
0%
#220
b1 '
1%
#240
0%
#260
0!
b0 '
1%
#280
0%
#300
1%
#320
0%
#340
1%
#360
0%
#380
1%
#400
0%
#420
0#
1%
#440
0%
#460
1!
b111111111 '
1"
1%
b111111111 $
b111111111 &
#480
0%
#500
1#
0"
1%
#520
0%
#540
b11111111 '
1%
#560
0%
#580
b1111111 '
1%
#600
0%
#620
b111111 '
1%
#640
0%
#660
b11111 '
1%
#680
0%
#700
b1111 '
1%
#720
0%
#740
b111 '
1%
#760
0%
#780
b11 '
1%
#800
0%
#820
b1 '
1%
#840
0%
#860
0#
1%
#880
0%
#900
0!
b10101010 '
1"
1%
b10101010 $
b10101010 &
#920
0%
#940
1#
0"
1%
#960
0%
#980
1!
b1010101 '
1%
#1000
0%
#1020
0!
b101010 '
1%
#1040
0%
#1060
1!
b10101 '
1%
#1080
0%
#1100
0!
b1010 '
1%
#1120
0%
#1140
1!
b101 '
1%
#1160
0%
#1180
0!
b10 '
1%
#1200
0%
#1220
1!
b1 '
1%
#1240
0%
#1260
0!
b0 '
1%
#1280
0%
#1300
0#
1%
